{"success": true, "rgInventory": {"23697788568": {"id": "23697788568", "classid": "2727227113", "instanceid": "0", "amount": "1", "hide_in_china": 0, "pos": 1}, "23697588180": {"id": "23697588180", "classid": "3035568428", "instanceid": "302028390", "amount": "1", "hide_in_china": 0, "pos": 2}, "23326728438": {"id": "23326728438", "classid": "3106076656", "instanceid": "0", "amount": "1", "hide_in_china": 0, "pos": 3}, "23262447370": {"id": "23262447370", "classid": "3106076656", "instanceid": "0", "amount": "1", "hide_in_china": 0, "pos": 4}, "23255540388": {"id": "23255540388", "classid": "1989288046", "instanceid": "302028390", "amount": "1", "hide_in_china": 0, "pos": 5}, "23078503058": {"id": "23078503058", "classid": "3946324730", "instanceid": "0", "amount": "1", "hide_in_china": 0, "pos": 6}, "23071623780": {"id": "23071623780", "classid": "3035571108", "instanceid": "302028390", "amount": "1", "hide_in_china": 0, "pos": 7}, "23017180267": {"id": "23017180267", "classid": "1989281172", "instanceid": "302028390", "amount": "1", "hide_in_china": 0, "pos": 8}, "23006408112": {"id": "23006408112", "classid": "937244096", "instanceid": "188530139", "amount": "1", "hide_in_china": 0, "pos": 9}, "23002006609": {"id": "23002006609", "classid": "3106076656", "instanceid": "0", "amount": "1", "hide_in_china": 0, "pos": 10}, "22983308576": {"id": "22983308576", "classid": "310780294", "instanceid": "302028390", "amount": "1", "hide_in_china": 0, "pos": 11}, "22982588611": {"id": "22982588611", "classid": "2727227113", "instanceid": "0", "amount": "1", "hide_in_china": 0, "pos": 12}, "22202054242": {"id": "22202054242", "classid": "3106076656", "instanceid": "0", "amount": "1", "hide_in_china": 0, "pos": 13}, "22191779865": {"id": "22191779865", "classid": "1989308747", "instanceid": "302028390", "amount": "1", "hide_in_china": 0, "pos": 14}, "22059447515": {"id": "22059447515", "classid": "3946324730", "instanceid": "0", "amount": "1", "hide_in_china": 0, "pos": 15}, "22031573286": {"id": "22031573286", "classid": "3035573934", "instanceid": "302028390", "amount": "1", "hide_in_china": 0, "pos": 16}, "21922758676": {"id": "21922758676", "classid": "1989297071", "instanceid": "302028390", "amount": "1", "hide_in_china": 0, "pos": 17}, "21904052738": {"id": "21904052738", "classid": "2727227113", "instanceid": "0", "amount": "1", "hide_in_china": 0, "pos": 18}, "21796313305": {"id": "21796313305", "classid": "310777118", "instanceid": "302028390", "amount": "1", "hide_in_china": 0, "pos": 19}, "21731787492": {"id": "21731787492", "classid": "3946324730", "instanceid": "0", "amount": "1", "hide_in_china": 0, "pos": 20}, "21731293605": {"id": "21731293605", "classid": "1989304901", "instanceid": "302028390", "amount": "1", "hide_in_china": 0, "pos": 21}, "21542677888": {"id": "21542677888", "classid": "310776967", "instanceid": "302028390", "amount": "1", "hide_in_china": 0, "pos": 22}, "21392635494": {"id": "21392635494", "classid": "1923037342", "instanceid": "0", "amount": "1", "hide_in_china": 0, "pos": 23}, "21350064317": {"id": "21350064317", "classid": "310776711", "instanceid": "302028390", "amount": "1", "hide_in_china": 0, "pos": 24}, "21315666016": {"id": "21315666016", "classid": "1690096482", "instanceid": "0", "amount": "1", "hide_in_china": 0, "pos": 25}, "21303346415": {"id": "21303346415", "classid": "310776765", "instanceid": "302028390", "amount": "1", "hide_in_china": 0, "pos": 26}, "20369559261": {"id": "20369559261", "classid": "2948874694", "instanceid": "0", "amount": "1", "hide_in_china": 0, "pos": 27}, "18544663012": {"id": "18544663012", "classid": "1432174707", "instanceid": "0", "amount": "1", "hide_in_china": 0, "pos": 28}, "18490077722": {"id": "18490077722", "classid": "1989287937", "instanceid": "302028390", "amount": "1", "hide_in_china": 0, "pos": 29}, "18480292238": {"id": "18480292238", "classid": "2948874694", "instanceid": "0", "amount": "1", "hide_in_china": 0, "pos": 30}, "18474792489": {"id": "18474792489", "classid": "1989281736", "instanceid": "302028390", "amount": "1", "hide_in_china": 0, "pos": 31}, "18396880217": {"id": "18396880217", "classid": "1797256701", "instanceid": "0", "amount": "1", "hide_in_china": 0, "pos": 32}, "18367576742": {"id": "18367576742", "classid": "310820898", "instanceid": "302028390", "amount": "1", "hide_in_china": 0, "pos": 33}, "18331147562": {"id": "18331147562", "classid": "1923037342", "instanceid": "0", "amount": "1", "hide_in_china": 0, "pos": 34}, "18302167195": {"id": "18302167195", "classid": "469443670", "instanceid": "302028390", "amount": "1", "hide_in_china": 0, "pos": 35}, "18272611048": {"id": "18272611048", "classid": "1797256701", "instanceid": "0", "amount": "1", "hide_in_china": 0, "pos": 36}, "18271929268": {"id": "18271929268", "classid": "310779639", "instanceid": "302028390", "amount": "1", "hide_in_china": 0, "pos": 37}, "15859848466": {"id": "15859848466", "classid": "2521767801", "instanceid": "0", "amount": "1", "hide_in_china": 0, "pos": 38}, "15859715971": {"id": "15859715971", "classid": "1989302515", "instanceid": "302028390", "amount": "1", "hide_in_china": 0, "pos": 39}, "15774680821": {"id": "15774680821", "classid": "2727227113", "instanceid": "0", "amount": "1", "hide_in_china": 0, "pos": 40}, "15773783341": {"id": "15773783341", "classid": "1989295965", "instanceid": "302028390", "amount": "1", "hide_in_china": 0, "pos": 41}, "15731289847": {"id": "15731289847", "classid": "2066632015", "instanceid": "0", "amount": "1", "hide_in_china": 0, "pos": 42}, "15724358997": {"id": "15724358997", "classid": "1989273941", "instanceid": "302028390", "amount": "1", "hide_in_china": 0, "pos": 43}, "15700233653": {"id": "15700233653", "classid": "2727227113", "instanceid": "0", "amount": "1", "hide_in_china": 0, "pos": 44}, "15628135912": {"id": "15628135912", "classid": "1989274855", "instanceid": "302028390", "amount": "1", "hide_in_china": 0, "pos": 45}, "15545161033": {"id": "15545161033", "classid": "310776717", "instanceid": "302028390", "amount": "1", "hide_in_china": 0, "pos": 46}}, "rgCurrency": [], "rgDescriptions": {"2727227113_0": {"appid": "730", "classid": "2727227113", "instanceid": "0", "icon_url": "-9a81dlWLwJ2UUGcVs_nsVtzdOEdtWwKGZZLQHTxDZ7I56KU0Zwwo4NUX4oFJZEHLbXU5A1PIYQNqhpOSV-fRPasw8rsUFJ5KBFZv668FFY5naqQIz4R7Yjix9bZkvKiZrmAzzlTu5AoibiT8d_x21Wy8hY_MWz1doSLMlhpM3FKbNs", "icon_drag_url": "", "name": "Clutch Case", "market_hash_name": "Clutch Case", "market_name": "Clutch Case", "name_color": "D2D2D2", "background_color": "", "type": "Base Grade Container", "tradable": 1, "marketable": 1, "commodity": 1, "market_tradable_restriction": "7", "market_buy_country_restriction": "FR", "descriptions": [{"type": "html", "value": " "}, {"type": "html", "value": "Container Series #238", "color": "99ccff"}, {"type": "html", "value": " "}, {"type": "html", "value": "Contains one of the following:"}, {"type": "html", "value": "PP-Bizon | Night Riot", "color": "4b69ff"}, {"type": "html", "value": "Five-SeveN | Flame Test", "color": "4b69ff"}, {"type": "html", "value": "MP9 | Black Sand", "color": "4b69ff"}, {"type": "html", "value": "P2000 | Urban Hazard", "color": "4b69ff"}, {"type": "html", "value": "R8 Revolver | Grip", "color": "4b69ff"}, {"type": "html", "value": "SG 553 | Aloha", "color": "4b69ff"}, {"type": "html", "value": "XM1014 | Oxide Blaze", "color": "4b69ff"}, {"type": "html", "value": "Glock-18 | Moonrise", "color": "8847ff"}, {"type": "html", "value": "Negev | Lionfish", "color": "8847ff"}, {"type": "html", "value": "Nova | Wild Six", "color": "8847ff"}, {"type": "html", "value": "MAG-7 | SWAG-7", "color": "8847ff"}, {"type": "html", "value": "UMP-45 | Arctic Wolf", "color": "8847ff"}, {"type": "html", "value": "AUG | Stymphalian", "color": "d32ce6"}, {"type": "html", "value": "AWP | Mortis", "color": "d32ce6"}, {"type": "html", "value": "USP-S | Cortex", "color": "d32ce6"}, {"type": "html", "value": "M4A4 | Neo-Noir", "color": "eb4b4b"}, {"type": "html", "value": "MP7 | Bloodsport", "color": "eb4b4b"}, {"type": "html", "value": "or the Exceedingly Rare Gloves!", "color": "ffd700"}, {"type": "html", "value": " "}, {"type": "html", "value": "", "color": "00a000", "app_data": {"limited": 1}}], "tags": [{"internal_name": "CSGO_Type_WeaponCase", "name": "Container", "category": "Type", "category_name": "Type"}, {"internal_name": "set_community_19", "name": "The Clutch Collection", "category": "ItemSet", "category_name": "Collection"}, {"internal_name": "normal", "name": "Normal", "category": "Quality", "category_name": "Category"}, {"internal_name": "Rarity_Common", "name": "Base Grade", "category": "Rarity", "color": "b0c3d9", "category_name": "Quality"}]}, "3035568428_302028390": {"appid": "730", "classid": "3035568428", "instanceid": "302028390", "icon_url": "-9a81dlWLwJ2UUGcVs_nsVtzdOEdtWwKGZZLQHTxDZ7I56KU0Zwwo4NUX4oFJZEHLbXH5ApeO4YmlhxYQknCRvCo04DEVlxkKgpouLWzKjhoyszMZD5W_-OxhoWSqPrxN7LEmyVQvcMi2r_Drd_x2VW2_0NrNmygJo6VJwFoZ1zV-1PoxenmjZ--uM_O1zI97VJyViud", "icon_url_large": "-9a81dlWLwJ2UUGcVs_nsVtzdOEdtWwKGZZLQHTxDZ7I56KU0Zwwo4NUX4oFJZEHLbXH5ApeO4YmlhxYQknCRvCo04DEVlxkKgpouLWzKjhoyszMZD5W_-OxhoWSqPrxN7LEm1Rd6dd2j6fAoIqm2AK280A4YjihIIaSJwNtY1DQr1box-rqhJTquJrAwXthvnIl-z-DyCDq5n8c", "icon_drag_url": "", "name": "Nova | Mandrel", "market_hash_name": "Nova | Mandrel (Field-Tested)", "market_name": "Nova | Mandrel (Field-Tested)", "name_color": "D2D2D2", "background_color": "", "type": "Consumer Grade Shotgun", "tradable": 1, "marketable": 1, "commodity": 0, "market_tradable_restriction": "7", "descriptions": [{"type": "html", "value": "Exterior: Field-Tested"}, {"type": "html", "value": " "}, {"type": "html", "value": "The Nova's rock-bottom price tag makes it a great ambush weapon for a cash-strapped team. A grayscale hydrographic pattern of interweaving pipes has been applied.\n\n<i>Shaping rounds with each shot</i>"}, {"type": "html", "value": " "}, {"type": "html", "value": "The 2018 Nuke Collection", "color": "9da1a9", "app_data": {"def_index": "65535", "is_itemset_name": 1}}, {"type": "html", "value": " "}], "actions": [{"name": "Inspect in Game...", "link": "steam://rungame/730/76561202255233023/+csgo_econ_action_preview%20S%owner_steamid%A%assetid%D7829688281397233823"}], "market_actions": [{"name": "Inspect in Game...", "link": "steam://rungame/730/76561202255233023/+csgo_econ_action_preview%20M%listingid%A%assetid%D7829688281397233823"}], "tags": [{"internal_name": "CSGO_Type_Shotgun", "name": "Shotgun", "category": "Type", "category_name": "Type"}, {"internal_name": "weapon_nova", "name": "Nova", "category": "Weapon", "category_name": "Weapon"}, {"internal_name": "set_nuke_2", "name": "The 2018 Nuke Collection", "category": "ItemSet", "category_name": "Collection"}, {"internal_name": "normal", "name": "Normal", "category": "Quality", "category_name": "Category"}, {"internal_name": "Rarity_Common_Weapon", "name": "Consumer Grade", "category": "Rarity", "color": "b0c3d9", "category_name": "Quality"}, {"internal_name": "WearCategory2", "name": "Field-Tested", "category": "Exterior", "category_name": "Exterior"}]}, "3106076656_0": {"appid": "730", "classid": "3106076656", "instanceid": "0", "icon_url": "-9a81dlWLwJ2UUGcVs_nsVtzdOEdtWwKGZZLQHTxDZ7I56KU0Zwwo4NUX4oFJZEHLbXU5A1PIYQNqhpOSV-fRPasw8rsUFJ5KBFZv668FFUxnaPLJz5H74y1xtTcz6etNumIx29U6Zd3j7yQoYih3lG1-UJqY27xJIeLMlhpaD9Aclo", "icon_drag_url": "", "name": "Danger Zone Case", "market_hash_name": "Danger Zone Case", "market_name": "Danger Zone Case", "name_color": "D2D2D2", "background_color": "", "type": "Base Grade Container", "tradable": 1, "marketable": 1, "commodity": 1, "market_tradable_restriction": "7", "market_buy_country_restriction": "FR", "descriptions": [{"type": "html", "value": " "}, {"type": "html", "value": "Container Series #259", "color": "99ccff"}, {"type": "html", "value": " "}, {"type": "html", "value": "Contains one of the following:"}, {"type": "html", "value": "MP9 | Modest Threat", "color": "4b69ff"}, {"type": "html", "value": "Glock-18 | Oxide Blaze", "color": "4b69ff"}, {"type": "html", "value": "Nova | Wood Fired", "color": "4b69ff"}, {"type": "html", "value": "M4A4 | Magnesium", "color": "4b69ff"}, {"type": "html", "value": "Sawed-Off | Black Sand", "color": "4b69ff"}, {"type": "html", "value": "SG 553 | Danger Close", "color": "4b69ff"}, {"type": "html", "value": "Tec-9 | Fubar", "color": "4b69ff"}, {"type": "html", "value": "G3SG1 | Scavenger", "color": "8847ff"}, {"type": "html", "value": "Galil AR | Signal", "color": "8847ff"}, {"type": "html", "value": "MAC-10 | Pipe Down", "color": "8847ff"}, {"type": "html", "value": "P250 | Nevermore", "color": "8847ff"}, {"type": "html", "value": "USP-S | Flashback", "color": "8847ff"}, {"type": "html", "value": "UMP-45 | Momentum", "color": "d32ce6"}, {"type": "html", "value": "Desert Eagle | Mecha Industries", "color": "d32ce6"}, {"type": "html", "value": "MP5-SD | Phosphor", "color": "d32ce6"}, {"type": "html", "value": "AK-47 | Asiimov", "color": "eb4b4b"}, {"type": "html", "value": "AWP | Neo-Noir", "color": "eb4b4b"}, {"type": "html", "value": "or an Exceedingly Rare Special Item!", "color": "ffd700"}, {"type": "html", "value": " "}, {"type": "html", "value": "", "color": "00a000", "app_data": {"limited": 1}}], "tags": [{"internal_name": "CSGO_Type_WeaponCase", "name": "Container", "category": "Type", "category_name": "Type"}, {"internal_name": "set_community_21", "name": "The Danger Zone Collection", "category": "ItemSet", "category_name": "Collection"}, {"internal_name": "normal", "name": "Normal", "category": "Quality", "category_name": "Category"}, {"internal_name": "Rarity_Common", "name": "Base Grade", "category": "Rarity", "color": "b0c3d9", "category_name": "Quality"}]}, "1989288046_302028390": {"appid": "730", "classid": "1989288046", "instanceid": "302028390", "icon_url": "IzMF03bi9WpSBq-S-ekoE33L-iLqGFHVaU25ZzQNQcXdB2ozio1RrlIWFK3UfvMYB8UsvjiMXojflsZalyxSh31CIyHz2GZ-KuFpPsrTzBG0rO2BBTqjOWGReHiLGV9uH7ZbY2ve9zKtsemWRG3BEuotQg9Ve6pX-m1IPMGNIVJjg5FYpGm3hUloEgIhYslfLQrvyXcXZOtqTL8A", "icon_url_large": "IzMF03bi9WpSBq-S-ekoE33L-iLqGFHVaU25ZzQNQcXdB2ozio1RrlIWFK3UfvMYB8UsvjiMXojflsZalyxSh31CIyHz2GZ-KuFpPsrTzBG0rO2BBUv7aSXDKm-OSApqHrZdNGverGai5rnCRT2YFLwsF1oCePNR-jVKPM7dNkQ41dUC5XW2kAJ-ERonYMhTfBuy2ngKbLhxyyIWcOj0CFKa", "icon_drag_url": "", "name": "Sealed Graffiti | Toasted (War Pig Pink)", "market_hash_name": "Sealed Graffiti | Toasted (War Pig Pink)", "market_name": "Sealed Graffiti | Toasted (War Pig Pink)", "name_color": "D2D2D2", "background_color": "", "type": "Base Grade Graffiti", "tradable": 1, "marketable": 1, "commodity": 1, "market_tradable_restriction": "7", "descriptions": [{"type": "html", "value": "This is a sealed container of a graffiti pattern. Once this graffiti pattern is unsealed, it will provide you with enough charges to apply the graffiti pattern <b>50</b> times to the in-game world."}, {"type": "html", "value": " "}, {"type": "html", "value": "", "color": "00a000", "app_data": {"limited": 1}}], "actions": [{"name": "Inspect in Game...", "link": "steam://rungame/730/76561202255233023/+csgo_econ_action_preview%20S%owner_steamid%A%assetid%D5539607051697130344"}], "market_actions": [{"name": "Inspect in Game...", "link": "steam://rungame/730/76561202255233023/+csgo_econ_action_preview%20M%listingid%A%assetid%D5539607051697130344"}], "tags": [{"internal_name": "CSGO_Type_Spray", "name": "Graffiti", "category": "Type", "category_name": "Type"}, {"internal_name": "normal", "name": "Normal", "category": "Quality", "category_name": "Category"}, {"internal_name": "Rarity_Common", "name": "Base Grade", "category": "Rarity", "color": "b0c3d9", "category_name": "Quality"}, {"internal_name": "Tint18", "name": "War Pig Pink", "category": "SprayColorCategory", "category_name": "Graffiti Color"}]}, "3946324730_0": {"appid": "730", "classid": "3946324730", "instanceid": "0", "icon_url": "-9a81dlWLwJ2UUGcVs_nsVtzdOEdtWwKGZZLQHTxDZ7I56KU0Zwwo4NUX4oFJZEHLbXU5A1PIYQNqhpOSV-fRPasw8rsUFJ5KBFZv668FFU2nfGaJG0btN2wwYHfxa-hY-uFxj4Dv50nj7uXpI7w3AewrhBpMWH6d9CLMlhpEbAe-Zk", "icon_drag_url": "", "name": "Fracture Case", "market_hash_name": "Fracture Case", "market_name": "Fracture Case", "name_color": "D2D2D2", "background_color": "", "type": "Base Grade Container", "tradable": 1, "marketable": 1, "commodity": 1, "market_tradable_restriction": "7", "market_buy_country_restriction": "FR", "descriptions": [{"type": "html", "value": " "}, {"type": "html", "value": "Container Series #307", "color": "99ccff"}, {"type": "html", "value": " "}, {"type": "html", "value": "Contains one of the following:"}, {"type": "html", "value": "Negev | Ultralight", "color": "4b69ff"}, {"type": "html", "value": "P2000 | Gnarled", "color": "4b69ff"}, {"type": "html", "value": "SG 553 | Ol' Rusty", "color": "4b69ff"}, {"type": "html", "value": "SSG 08 | Mainframe 001", "color": "4b69ff"}, {"type": "html", "value": "P250 | Cassette", "color": "4b69ff"}, {"type": "html", "value": "P90 | Freight", "color": "4b69ff"}, {"type": "html", "value": "PP-Bizon | Runic", "color": "4b69ff"}, {"type": "html", "value": "MAG-7 | Monster Call", "color": "8847ff"}, {"type": "html", "value": "Tec-9 | Brother", "color": "8847ff"}, {"type": "html", "value": "MAC-10 | Allure", "color": "8847ff"}, {"type": "html", "value": "Galil AR | Connexion", "color": "8847ff"}, {"type": "html", "value": "MP5-SD | Kitbash", "color": "8847ff"}, {"type": "html", "value": "M4A4 | Tooth Fairy", "color": "d32ce6"}, {"type": "html", "value": "Glock-18 | Vogue", "color": "d32ce6"}, {"type": "html", "value": "XM1014 | Entombed", "color": "d32ce6"}, {"type": "html", "value": "Desert Eagle | Printstream", "color": "eb4b4b"}, {"type": "html", "value": "AK-47 | Legion of Anubis", "color": "eb4b4b"}, {"type": "html", "value": "or an Exceedingly Rare Special Item!", "color": "ffd700"}, {"type": "html", "value": " "}, {"type": "html", "value": "", "color": "00a000", "app_data": {"limited": 1}}], "tags": [{"internal_name": "CSGO_Type_WeaponCase", "name": "Container", "category": "Type", "category_name": "Type"}, {"internal_name": "set_community_26", "name": "The Fracture Collection", "category": "ItemSet", "category_name": "Collection"}, {"internal_name": "normal", "name": "Normal", "category": "Quality", "category_name": "Category"}, {"internal_name": "Rarity_Common", "name": "Base Grade", "category": "Rarity", "color": "b0c3d9", "category_name": "Quality"}]}, "3035571108_302028390": {"appid": "730", "classid": "3035571108", "instanceid": "302028390", "icon_url": "-9a81dlWLwJ2UUGcVs_nsVtzdOEdtWwKGZZLQHTxDZ7I56KU0Zwwo4NUX4oFJZEHLbXH5ApeO4YmlhxYQknCRvCo04DEVlxkKgpotLO_JAlf2-r3czFX6cyknY6fqOD8Oq_UqWZU7Mxkh6fFo9T0iwK2rUFrNmqlIIXAJlA7YV2F-FXryLzsgJO4u5TOm3tn7id3-z-DyGqIfxJS", "icon_url_large": "-9a81dlWLwJ2UUGcVs_nsVtzdOEdtWwKGZZLQHTxDZ7I56KU0Zwwo4NUX4oFJZEHLbXH5ApeO4YmlhxYQknCRvCo04DEVlxkKgpotLO_JAlf2-r3czFX6cyknY6fqOD8Oq_UqWZU7Mxkh9bN9J7yjRqw_Us9MG-hcoSSJwVoZVuFrge7weu6h5Lptc_KzHdnvSklt3bZyxLin1gSObKbZrjQ", "icon_drag_url": "", "name": "PP-Bizon | Facility Sketch", "market_hash_name": "PP-Bizon | Facility Sketch (Field-Tested)", "market_name": "PP-Bizon | Facility Sketch (Field-Tested)", "name_color": "D2D2D2", "background_color": "", "type": "Consumer Grade SMG", "tradable": 1, "marketable": 1, "commodity": 0, "market_tradable_restriction": "7", "descriptions": [{"type": "html", "value": "Exterior: Field-Tested"}, {"type": "html", "value": " "}, {"type": "html", "value": "The Bizon SMG is low-damage, but offers a uniquely designed high-capacity drum magazine that reloads quickly. A grayscale hydrographic pattern resembling a nuclear power plant has been applied.\n\n<i>\"Your point of entry is the ventilation system\"</i>"}, {"type": "html", "value": " "}, {"type": "html", "value": "The 2018 Nuke Collection", "color": "9da1a9", "app_data": {"def_index": "65535", "is_itemset_name": 1}}, {"type": "html", "value": " "}], "actions": [{"name": "Inspect in Game...", "link": "steam://rungame/730/76561202255233023/+csgo_econ_action_preview%20S%owner_steamid%A%assetid%D9369966541050968124"}], "market_actions": [{"name": "Inspect in Game...", "link": "steam://rungame/730/76561202255233023/+csgo_econ_action_preview%20M%listingid%A%assetid%D9369966541050968124"}], "tags": [{"internal_name": "CSGO_Type_SMG", "name": "SMG", "category": "Type", "category_name": "Type"}, {"internal_name": "weapon_bizon", "name": "PP-Bizon", "category": "Weapon", "category_name": "Weapon"}, {"internal_name": "set_nuke_2", "name": "The 2018 Nuke Collection", "category": "ItemSet", "category_name": "Collection"}, {"internal_name": "normal", "name": "Normal", "category": "Quality", "category_name": "Category"}, {"internal_name": "Rarity_Common_Weapon", "name": "Consumer Grade", "category": "Rarity", "color": "b0c3d9", "category_name": "Quality"}, {"internal_name": "WearCategory2", "name": "Field-Tested", "category": "Exterior", "category_name": "Exterior"}]}, "1989281172_302028390": {"appid": "730", "classid": "1989281172", "instanceid": "302028390", "icon_url": "IzMF03bi9WpSBq-S-ekoE33L-iLqGFHVaU25ZzQNQcXdB2ozio1RrlIWFK3UfvMYB8UsvjiMXojflsZalyxSh31CIyHz2GZ-KuFpPsrTzBG0pO-CI3r-Zj3FYSeJGA44TOJfYW7YqjD2sOXHQjrKQO0uRAAHK6tR-mEdPsvbO0Zo3YUVu2u_0UdyEhk6f9BKZAarxm1OMLt8miUU6yU0OcA", "icon_url_large": "IzMF03bi9WpSBq-S-ekoE33L-iLqGFHVaU25ZzQNQcXdB2ozio1RrlIWFK3UfvMYB8UsvjiMXojflsZalyxSh31CIyHz2GZ-KuFpPsrTzBG0pO-CI3r-Zj3FEC3YDlltU-UKN2rd9zSj4-_FFm3JFOskFw9SdfRR9WBKaJyNOhdpgdIP8me8xBMzDhgvNMZJfACpx2EfJbQ1xDhPJM1bm3CmeFRuEYY", "icon_drag_url": "", "name": "Sealed Graffiti | Ninja (Violent Violet)", "market_hash_name": "Sealed Graffiti | Ninja (Violent Violet)", "market_name": "Sealed Graffiti | Ninja (Violent Violet)", "name_color": "D2D2D2", "background_color": "", "type": "Base Grade Graffiti", "tradable": 1, "marketable": 1, "commodity": 1, "market_tradable_restriction": "7", "descriptions": [{"type": "html", "value": "This is a sealed container of a graffiti pattern. Once this graffiti pattern is unsealed, it will provide you with enough charges to apply the graffiti pattern <b>50</b> times to the in-game world."}, {"type": "html", "value": " "}, {"type": "html", "value": "", "color": "00a000", "app_data": {"limited": 1}}], "actions": [{"name": "Inspect in Game...", "link": "steam://rungame/730/76561202255233023/+csgo_econ_action_preview%20S%owner_steamid%A%assetid%D14150311546012346724"}], "market_actions": [{"name": "Inspect in Game...", "link": "steam://rungame/730/76561202255233023/+csgo_econ_action_preview%20M%listingid%A%assetid%D14150311546012346724"}], "tags": [{"internal_name": "CSGO_Type_Spray", "name": "Graffiti", "category": "Type", "category_name": "Type"}, {"internal_name": "normal", "name": "Normal", "category": "Quality", "category_name": "Category"}, {"internal_name": "Rarity_Common", "name": "Base Grade", "category": "Rarity", "color": "b0c3d9", "category_name": "Quality"}, {"internal_name": "Tint14", "name": "Violent Violet", "category": "SprayColorCategory", "category_name": "Graffiti Color"}]}, "937244096_188530139": {"appid": "730", "classid": "937244096", "instanceid": "188530139", "icon_url": "-9a81dlWLwJ2UUGcVs_nsVtzdOEdtWwKGZZLQHTxDZ7I56KU0Zwwo4NUX4oFJZEHLbXH5ApeO4YmlhxYQknCRvCo04DEVlxkKgpopujwezhhwszYI2gS09-5mpSEguXLP7LWnn8f7sR33-uSpdn23gyw8xY9YWr7JYKUdAVsYQnW8wXvl7_ohpe07pXIwWwj5HeF0_VeIQ", "icon_url_large": "-9a81dlWLwJ2UUGcVs_nsVtzdOEdtWwKGZZLQHTxDZ7I56KU0Zwwo4NUX4oFJZEHLbXH5ApeO4YmlhxYQknCRvCo04DEVlxkKgpopujwezhhwszYI2gS09-5mpSEguXLP7LWnn9u5MRjjeyP843z3Vbn-0Y_ZWGnLNPEcAU2YFzR_FLswb_pjMLt6szOynNr6Cgj7WGdwUK-H5W5kA", "icon_drag_url": "", "name": "P250 | Valence", "market_hash_name": "P250 | Valence (Minimal Wear)", "market_name": "P250 | Valence (Minimal Wear)", "name_color": "D2D2D2", "background_color": "", "type": "Mil-Spec Grade Pistol", "tradable": 1, "marketable": 1, "commodity": 0, "market_tradable_restriction": "7", "descriptions": [{"type": "html", "value": "Exterior: Minimal Wear"}, {"type": "html", "value": " "}, {"type": "html", "value": "A low-recoil firearm with a high rate of fire, the P250 is a relatively inexpensive choice against armored opponents. It has been custom painted in a modern blue and grey design that complements the weapon's form.\n\n<i>Your skills aren't in question, your attitude is - The Teacher and The Iconoclast Part 1</i>"}, {"type": "html", "value": " "}, {"type": "html", "value": "The Chroma 2 Collection", "color": "9da1a9", "app_data": {"def_index": "65535", "is_itemset_name": 1}}, {"type": "html", "value": " "}], "actions": [{"name": "Inspect in Game...", "link": "steam://rungame/730/76561202255233023/+csgo_econ_action_preview%20S%owner_steamid%A%assetid%D10268779510197027688"}], "market_actions": [{"name": "Inspect in Game...", "link": "steam://rungame/730/76561202255233023/+csgo_econ_action_preview%20M%listingid%A%assetid%D10268779510197027688"}], "tags": [{"internal_name": "CSGO_Type_Pistol", "name": "Pistol", "category": "Type", "category_name": "Type"}, {"internal_name": "weapon_p250", "name": "P250", "category": "Weapon", "category_name": "Weapon"}, {"internal_name": "set_community_7", "name": "The Chroma 2 Collection", "category": "ItemSet", "category_name": "Collection"}, {"internal_name": "normal", "name": "Normal", "category": "Quality", "category_name": "Category"}, {"internal_name": "Rarity_Rare_Weapon", "name": "Mil-Spec Grade", "category": "Rarity", "color": "4b69ff", "category_name": "Quality"}, {"internal_name": "WearCategory1", "name": "Minimal Wear", "category": "Exterior", "category_name": "Exterior"}]}, "310780294_302028390": {"appid": "730", "classid": "310780294", "instanceid": "302028390", "icon_url": "-9a81dlWLwJ2UUGcVs_nsVtzdOEdtWwKGZZLQHTxDZ7I56KU0Zwwo4NUX4oFJZEHLbXH5ApeO4YmlhxYQknCRvCo04DEVlxkKgpovrG1eVcwg8zAaAJF_t24nZSOqPv9NLPF2DgB7JNw3LHCoN6niVHhrxdsMD_0dYCSJwY5NAuDqFe4krjqhcS8uM7XiSw0dqnDKw8", "icon_url_large": "-9a81dlWLwJ2UUGcVs_nsVtzdOEdtWwKGZZLQHTxDZ7I56KU0Zwwo4NUX4oFJZEHLbXH5ApeO4YmlhxYQknCRvCo04DEVlxkKgpovrG1eVcwg8zAaAJF_t24nZSOqPv9NLPFqWdQ-sJ0xLqR8dr03gy3_kFuMjz2cNKVIVA5MF7Xr1G5lL2815C678vMySBjvnM8pSGK6X0incY", "icon_drag_url": "", "name": "P2000 | Granite Marbleized", "market_hash_name": "P2000 | Granite Marbleized (Minimal Wear)", "market_name": "P2000 | Granite Marbleized (Minimal Wear)", "name_color": "D2D2D2", "background_color": "", "type": "Industrial Grade Pistol", "tradable": 1, "marketable": 1, "commodity": 0, "market_tradable_restriction": "7", "descriptions": [{"type": "html", "value": "Exterior: Minimal Wear"}, {"type": "html", "value": " "}, {"type": "html", "value": "Accurate and controllable, the German-made P2000 is a serviceable first-round pistol that works best against unarmored opponents. It has been painted in a marbleized pattern."}, {"type": "html", "value": " "}, {"type": "html", "value": "The Italy Collection", "color": "9da1a9", "app_data": {"def_index": "65535", "is_itemset_name": 1}}, {"type": "html", "value": " "}], "actions": [{"name": "Inspect in Game...", "link": "steam://rungame/730/76561202255233023/+csgo_econ_action_preview%20S%owner_steamid%A%assetid%D17187500647393700356"}], "market_actions": [{"name": "Inspect in Game...", "link": "steam://rungame/730/76561202255233023/+csgo_econ_action_preview%20M%listingid%A%assetid%D17187500647393700356"}], "tags": [{"internal_name": "CSGO_Type_Pistol", "name": "Pistol", "category": "Type", "category_name": "Type"}, {"internal_name": "weapon_hkp2000", "name": "P2000", "category": "Weapon", "category_name": "Weapon"}, {"internal_name": "set_italy", "name": "The Italy Collection", "category": "ItemSet", "category_name": "Collection"}, {"internal_name": "normal", "name": "Normal", "category": "Quality", "category_name": "Category"}, {"internal_name": "Rarity_Uncommon_Weapon", "name": "Industrial Grade", "category": "Rarity", "color": "5e98d9", "category_name": "Quality"}, {"internal_name": "WearCategory1", "name": "Minimal Wear", "category": "Exterior", "category_name": "Exterior"}]}, "1989308747_302028390": {"appid": "730", "classid": "1989308747", "instanceid": "302028390", "icon_url": "IzMF03bi9WpSBq-S-ekoE33L-iLqGFHVaU25ZzQNQcXdB2ozio1RrlIWFK3UfvMYB8UsvjiMXojflsZalyxSh31CIyHz2GZ-KuFpPsrTzBG0pO-CI3DyeyfFJjOXS1s9SOJZZ2rb9zXx5OrAFjDOE-1_R1pQKaNW8TUbOs-LPxJo1I8JqiuomUM7HRkkfddLZQOvw2QfKOAnyXdKJ5ks7rdF3g", "icon_url_large": "IzMF03bi9WpSBq-S-ekoE33L-iLqGFHVaU25ZzQNQcXdB2ozio1RrlIWFK3UfvMYB8UsvjiMXojflsZalyxSh31CIyHz2GZ-KuFpPsrTzBG0pO-CI3DyeyfFJjPmEF96GuZAMTuMrTGktOuSF2qcE70sRA4NKaJQo2IdOpqAaUQ-0oNY_TPok0d4S1g4fMIAcwC3xWYeJLExwTEePJYAyCL4dJZ-qDqEjQ", "icon_drag_url": "", "name": "Sealed Graffiti | QQ (Bazooka Pink)", "market_hash_name": "Sealed Graffiti | QQ (Bazooka Pink)", "market_name": "Sealed Graffiti | QQ (Bazooka Pink)", "name_color": "D2D2D2", "background_color": "", "type": "Base Grade Graffiti", "tradable": 1, "marketable": 1, "commodity": 1, "market_tradable_restriction": "7", "descriptions": [{"type": "html", "value": "This is a sealed container of a graffiti pattern. Once this graffiti pattern is unsealed, it will provide you with enough charges to apply the graffiti pattern <b>50</b> times to the in-game world."}, {"type": "html", "value": " "}, {"type": "html", "value": "", "color": "00a000", "app_data": {"limited": 1}}], "actions": [{"name": "Inspect in Game...", "link": "steam://rungame/730/76561202255233023/+csgo_econ_action_preview%20S%owner_steamid%A%assetid%D14179249062595043788"}], "market_actions": [{"name": "Inspect in Game...", "link": "steam://rungame/730/76561202255233023/+csgo_econ_action_preview%20M%listingid%A%assetid%D14179249062595043788"}], "tags": [{"internal_name": "CSGO_Type_Spray", "name": "Graffiti", "category": "Type", "category_name": "Type"}, {"internal_name": "normal", "name": "Normal", "category": "Quality", "category_name": "Category"}, {"internal_name": "Rarity_Common", "name": "Base Grade", "category": "Rarity", "color": "b0c3d9", "category_name": "Quality"}, {"internal_name": "Tint16", "name": "Bazooka Pink", "category": "SprayColorCategory", "category_name": "Graffiti Color"}]}, "3035573934_302028390": {"appid": "730", "classid": "3035573934", "instanceid": "302028390", "icon_url": "-9a81dlWLwJ2UUGcVs_nsVtzdOEdtWwKGZZLQHTxDZ7I56KU0Zwwo4NUX4oFJZEHLbXH5ApeO4YmlhxYQknCRvCo04DEVlxkKgpopujwezhoyszMZD5W_-O0mJWOqPrxN7LEmyVS7cZw3LHEpNug2QOyrxE6Y2D1Io6XdA5tYwuGr1C6kO_uh8K1vsiY1zI97bSWXiZH", "icon_url_large": "-9a81dlWLwJ2UUGcVs_nsVtzdOEdtWwKGZZLQHTxDZ7I56KU0Zwwo4NUX4oFJZEHLbXH5ApeO4YmlhxYQknCRvCo04DEVlxkKgpopujwezhoyszMZD5W_-O0mJWOqPrxN7LEm1Rd6dd2j6fC8I_03gyx-kRpYm6lcNTDcg84Z1DS_Fntw7250Je47ZzIyyZquHVz-z-DyC90_rWf", "icon_drag_url": "", "name": "P250 | Exchanger", "market_hash_name": "P250 | Exchanger (Field-Tested)", "market_name": "P250 | Exchanger (Field-Tested)", "name_color": "D2D2D2", "background_color": "", "type": "Mil-Spec Grade Pistol", "tradable": 1, "marketable": 1, "commodity": 0, "market_tradable_restriction": "7", "descriptions": [{"type": "html", "value": "Exterior: Field-Tested"}, {"type": "html", "value": " "}, {"type": "html", "value": "A low-recoil firearm with a high rate of fire, the P250 is a relatively inexpensive choice against armored opponents. A hydrographic pattern of interweaving pipes has been applied.\n\n<i>\"My life for yours\"</i>"}, {"type": "html", "value": " "}, {"type": "html", "value": "The 2018 Nuke Collection", "color": "9da1a9", "app_data": {"def_index": "65535", "is_itemset_name": 1}}, {"type": "html", "value": " "}], "actions": [{"name": "Inspect in Game...", "link": "steam://rungame/730/76561202255233023/+csgo_econ_action_preview%20S%owner_steamid%A%assetid%D13866025296298297732"}], "market_actions": [{"name": "Inspect in Game...", "link": "steam://rungame/730/76561202255233023/+csgo_econ_action_preview%20M%listingid%A%assetid%D13866025296298297732"}], "tags": [{"internal_name": "CSGO_Type_Pistol", "name": "Pistol", "category": "Type", "category_name": "Type"}, {"internal_name": "weapon_p250", "name": "P250", "category": "Weapon", "category_name": "Weapon"}, {"internal_name": "set_nuke_2", "name": "The 2018 Nuke Collection", "category": "ItemSet", "category_name": "Collection"}, {"internal_name": "normal", "name": "Normal", "category": "Quality", "category_name": "Category"}, {"internal_name": "Rarity_Rare_Weapon", "name": "Mil-Spec Grade", "category": "Rarity", "color": "4b69ff", "category_name": "Quality"}, {"internal_name": "WearCategory2", "name": "Field-Tested", "category": "Exterior", "category_name": "Exterior"}]}, "1989297071_302028390": {"appid": "730", "classid": "1989297071", "instanceid": "302028390", "icon_url": "IzMF03bi9WpSBq-S-ekoE33L-iLqGFHVaU25ZzQNQcXdB2ozio1RrlIWFK3UfvMYB8UsvjiMXojflsZalyxSh31CIyHz2GZ-KuFpPsrTzBG0qe6yEHX6ajPFYXXfHg06GbILMm2I_jun4eXAFjHJQel6EQEGLKdX9WMdaJ2PaxM0048Vu2u_0UdyEhk6f9BKZAarxm1ONOkmyyVH838oPMQ", "icon_url_large": "IzMF03bi9WpSBq-S-ekoE33L-iLqGFHVaU25ZzQNQcXdB2ozio1RrlIWFK3UfvMYB8UsvjiMXojflsZalyxSh31CIyHz2GZ-KuFpPsrTzBG0qe6yEHX6ajPFEC3YDlltU-ZWPGnQ-DHwtrmTFjmfQbt6S1tSK_cEpGBNbpqOORI83YEJ-zXtxRQzDhgvNMZJfACpx2EfJbQ1xDhPIJ8BynD1RkSdssc", "icon_drag_url": "", "name": "Sealed Graffiti | Lambda (War Pig Pink)", "market_hash_name": "Sealed Graffiti | Lambda (War Pig Pink)", "market_name": "Sealed Graffiti | Lambda (War Pig Pink)", "name_color": "D2D2D2", "background_color": "", "type": "Base Grade Graffiti", "tradable": 1, "marketable": 1, "commodity": 1, "market_tradable_restriction": "7", "descriptions": [{"type": "html", "value": "This is a sealed container of a graffiti pattern. Once this graffiti pattern is unsealed, it will provide you with enough charges to apply the graffiti pattern <b>50</b> times to the in-game world."}, {"type": "html", "value": " "}, {"type": "html", "value": "", "color": "00a000", "app_data": {"limited": 1}}], "actions": [{"name": "Inspect in Game...", "link": "steam://rungame/730/76561202255233023/+csgo_econ_action_preview%20S%owner_steamid%A%assetid%D643631995989010368"}], "market_actions": [{"name": "Inspect in Game...", "link": "steam://rungame/730/76561202255233023/+csgo_econ_action_preview%20M%listingid%A%assetid%D643631995989010368"}], "tags": [{"internal_name": "CSGO_Type_Spray", "name": "Graffiti", "category": "Type", "category_name": "Type"}, {"internal_name": "normal", "name": "Normal", "category": "Quality", "category_name": "Category"}, {"internal_name": "Rarity_Common", "name": "Base Grade", "category": "Rarity", "color": "b0c3d9", "category_name": "Quality"}, {"internal_name": "Tint18", "name": "War Pig Pink", "category": "SprayColorCategory", "category_name": "Graffiti Color"}]}, "310777118_302028390": {"appid": "730", "classid": "310777118", "instanceid": "302028390", "icon_url": "-9a81dlWLwJ2UUGcVs_nsVtzdOEdtWwKGZZLQHTxDZ7I56KU0Zwwo4NUX4oFJZEHLbXH5ApeO4YmlhxYQknCRvCo04DEVlxkKgpoor-mcjhzw8zFdC5K092kmZm0mvLwOq7c2DJSscFy2OiXpo_zi1fgqko6YmGhLNWWdVI_NFmC8lW3xOnt0cO5v5zXiSw00ze-NIQ", "icon_url_large": "-9a81dlWLwJ2UUGcVs_nsVtzdOEdtWwKGZZLQHTxDZ7I56KU0Zwwo4NUX4oFJZEHLbXH5ApeO4YmlhxYQknCRvCo04DEVlxkKgpoor-mcjhzw8zFdC5K092kmZm0mvLwOq7cqWdQ-sJ0xLDCrIj22lXi-BA6MDr3dY_Dcw5saQvT_QW_lO-9jZK1uZrLnSdmuSE8pSGKHoGgJ0Y", "icon_drag_url": "", "name": "Tec-9 | Army Mesh", "market_hash_name": "Tec-9 | Army Mesh (Field-Tested)", "market_name": "Tec-9 | Army Mesh (Field-Tested)", "name_color": "D2D2D2", "background_color": "", "type": "Consumer Grade Pistol", "tradable": 1, "marketable": 1, "commodity": 0, "market_tradable_restriction": "7", "descriptions": [{"type": "html", "value": "Exterior: Field-Tested"}, {"type": "html", "value": " "}, {"type": "html", "value": "An ideal pistol for the Terrorist on the move, the Tec-9 is lethal in close quarters and features a high magazine capacity. It has been spray-painted freehand using mesh fabric as a stencil."}, {"type": "html", "value": " "}, {"type": "html", "value": "The Safehouse Collection", "color": "9da1a9", "app_data": {"def_index": "65535", "is_itemset_name": 1}}, {"type": "html", "value": " "}], "actions": [{"name": "Inspect in Game...", "link": "steam://rungame/730/76561202255233023/+csgo_econ_action_preview%20S%owner_steamid%A%assetid%D3073366476494020062"}], "market_actions": [{"name": "Inspect in Game...", "link": "steam://rungame/730/76561202255233023/+csgo_econ_action_preview%20M%listingid%A%assetid%D3073366476494020062"}], "tags": [{"internal_name": "CSGO_Type_Pistol", "name": "Pistol", "category": "Type", "category_name": "Type"}, {"internal_name": "weapon_tec9", "name": "Tec-9", "category": "Weapon", "category_name": "Weapon"}, {"internal_name": "set_safehouse", "name": "The Safehouse Collection", "category": "ItemSet", "category_name": "Collection"}, {"internal_name": "normal", "name": "Normal", "category": "Quality", "category_name": "Category"}, {"internal_name": "Rarity_Common_Weapon", "name": "Consumer Grade", "category": "Rarity", "color": "b0c3d9", "category_name": "Quality"}, {"internal_name": "WearCategory2", "name": "Field-Tested", "category": "Exterior", "category_name": "Exterior"}]}, "1989304901_302028390": {"appid": "730", "classid": "1989304901", "instanceid": "302028390", "icon_url": "IzMF03bi9WpSBq-S-ekoE33L-iLqGFHVaU25ZzQNQcXdB2ozio1RrlIWFK3UfvMYB8UsvjiMXojflsZalyxSh31CIyHz2GZ-KuFpPsrTzBG0pe2YHnjyVzzNIy2XHQYwH-ddMDrQ-TKn4rydSm7PSLx9FwwCKaRV9GUfPszbPRRogdIJ8yuomUM7HRkkfddLZQOvw2QfKOAkniJGJJ5p5kj4nA", "icon_url_large": "IzMF03bi9WpSBq-S-ekoE33L-iLqGFHVaU25ZzQNQcXdB2ozio1RrlIWFK3UfvMYB8UsvjiMXojflsZalyxSh31CIyHz2GZ-KuFpPsrTzBG0pe2YHnjyVzzNIy3mEF96GuZAYT2I_TKn4OqQQ2rAQ-EoSwlRf6MN8TFBaMGLbBJo1tYI_DLoxRwuR1g4fMIAcwC3xWYeJLExwTEePJYDn3f0d5EunT1HQA", "icon_drag_url": "", "name": "Sealed Graffiti | Double (Cash Green)", "market_hash_name": "Sealed Graffiti | Double (Cash Green)", "market_name": "Sealed Graffiti | Double (Cash Green)", "name_color": "D2D2D2", "background_color": "", "type": "Base Grade Graffiti", "tradable": 1, "marketable": 1, "commodity": 1, "market_tradable_restriction": "7", "descriptions": [{"type": "html", "value": "This is a sealed container of a graffiti pattern. Once this graffiti pattern is unsealed, it will provide you with enough charges to apply the graffiti pattern <b>50</b> times to the in-game world."}, {"type": "html", "value": " "}, {"type": "html", "value": "", "color": "00a000", "app_data": {"limited": 1}}], "actions": [{"name": "Inspect in Game...", "link": "steam://rungame/730/76561202255233023/+csgo_econ_action_preview%20S%owner_steamid%A%assetid%D621641520782541258"}], "market_actions": [{"name": "Inspect in Game...", "link": "steam://rungame/730/76561202255233023/+csgo_econ_action_preview%20M%listingid%A%assetid%D621641520782541258"}], "tags": [{"internal_name": "CSGO_Type_Spray", "name": "Graffiti", "category": "Type", "category_name": "Type"}, {"internal_name": "normal", "name": "Normal", "category": "Quality", "category_name": "Category"}, {"internal_name": "Rarity_Common", "name": "Base Grade", "category": "Rarity", "color": "b0c3d9", "category_name": "Quality"}, {"internal_name": "Tint10", "name": "Cash Green", "category": "SprayColorCategory", "category_name": "Graffiti Color"}]}, "310776967_302028390": {"appid": "730", "classid": "310776967", "instanceid": "302028390", "icon_url": "-9a81dlWLwJ2UUGcVs_nsVtzdOEdtWwKGZZLQHTxDZ7I56KU0Zwwo4NUX4oFJZEHLbXH5ApeO4YmlhxYQknCRvCo04DEVlxkKgpouLWzKjhzw8zFdC5K092kl5SClMj3PLXFhGpC_Pp9g-7J4cL30AGyqEdqZW_2doaQIQRvYQ2Fq1i7xL_ojJK66ZvNzSNkvCEq7HvZgVXp1kdWkONk", "icon_url_large": "-9a81dlWLwJ2UUGcVs_nsVtzdOEdtWwKGZZLQHTxDZ7I56KU0Zwwo4NUX4oFJZEHLbXH5ApeO4YmlhxYQknCRvCo04DEVlxkKgpouLWzKjhzw8zFdC5K092kl5SClMj3PLXFhGpC_Pp9g-7J4bP5iUazrl0-a2yld4KTdAA7M1jVqVPvwbu61J-5uczOwHZl7yYm4S7amRS_iBxIcKUx0lJqDj1i", "icon_drag_url": "", "name": "Nova | Polar Mesh", "market_hash_name": "Nova | Polar Mesh (Minimal Wear)", "market_name": "Nova | Polar Mesh (Minimal Wear)", "name_color": "D2D2D2", "background_color": "", "type": "Consumer Grade Shotgun", "tradable": 1, "marketable": 1, "commodity": 0, "market_tradable_restriction": "7", "descriptions": [{"type": "html", "value": "Exterior: Minimal Wear"}, {"type": "html", "value": " "}, {"type": "html", "value": "The Nova's rock-bottom price tag makes it a great ambush weapon for a cash-strapped team. It has been spray-painted using mesh fencing and cardboard cutouts as stencils.\n\n<i>A predator is a predator, no matter the environment</i>"}, {"type": "html", "value": " "}, {"type": "html", "value": "The Train Collection", "color": "9da1a9", "app_data": {"def_index": "65535", "is_itemset_name": 1}}, {"type": "html", "value": " "}], "actions": [{"name": "Inspect in Game...", "link": "steam://rungame/730/76561202255233023/+csgo_econ_action_preview%20S%owner_steamid%A%assetid%D13835881349523876991"}], "market_actions": [{"name": "Inspect in Game...", "link": "steam://rungame/730/76561202255233023/+csgo_econ_action_preview%20M%listingid%A%assetid%D13835881349523876991"}], "tags": [{"internal_name": "CSGO_Type_Shotgun", "name": "Shotgun", "category": "Type", "category_name": "Type"}, {"internal_name": "weapon_nova", "name": "Nova", "category": "Weapon", "category_name": "Weapon"}, {"internal_name": "set_train", "name": "The Train Collection", "category": "ItemSet", "category_name": "Collection"}, {"internal_name": "normal", "name": "Normal", "category": "Quality", "category_name": "Category"}, {"internal_name": "Rarity_Common_Weapon", "name": "Consumer Grade", "category": "Rarity", "color": "b0c3d9", "category_name": "Quality"}, {"internal_name": "WearCategory1", "name": "Minimal Wear", "category": "Exterior", "category_name": "Exterior"}]}, "1923037342_0": {"appid": "730", "classid": "1923037342", "instanceid": "0", "icon_url": "-9a81dlWLwJ2UUGcVs_nsVtzdOEdtWwKGZZLQHTxDZ7I56KU0Zwwo4NUX4oFJZEHLbXU5A1PIYQNqhpOSV-fRPasw8rsVFx5KAVo5PSkKV4xhfGfKTgVvIXlxNPSwaOmMLiGwzgJvJMniO-Zoo_z2wXg-EVvfSmtc78HsNoy", "icon_drag_url": "", "name": "Gamma 2 Case", "market_hash_name": "Gamma 2 Case", "market_name": "Gamma 2 Case", "name_color": "D2D2D2", "background_color": "", "type": "Base Grade Container", "tradable": 1, "marketable": 1, "commodity": 1, "market_tradable_restriction": "7", "market_buy_country_restriction": "FR", "descriptions": [{"type": "html", "value": " "}, {"type": "html", "value": "Container Series #172", "color": "99ccff"}, {"type": "html", "value": " "}, {"type": "html", "value": "Contains one of the following:"}, {"type": "html", "value": "CZ75-Auto | Imprint", "color": "4b69ff"}, {"type": "html", "value": "Five-SeveN | Scumbria", "color": "4b69ff"}, {"type": "html", "value": "G3SG1 | Ventilator", "color": "4b69ff"}, {"type": "html", "value": "Negev | Dazzle", "color": "4b69ff"}, {"type": "html", "value": "P90 | Grim", "color": "4b69ff"}, {"type": "html", "value": "UMP-45 | Briefing", "color": "4b69ff"}, {"type": "html", "value": "XM1014 | Slipstream", "color": "4b69ff"}, {"type": "html", "value": "Desert Eagle | Directive", "color": "8847ff"}, {"type": "html", "value": "Glock-18 | Weasel", "color": "8847ff"}, {"type": "html", "value": "MAG-7 | Petroglyph", "color": "8847ff"}, {"type": "html", "value": "SCAR-20 | Powercore", "color": "8847ff"}, {"type": "html", "value": "SG 553 | Triarch", "color": "8847ff"}, {"type": "html", "value": "AUG | Syd Mead", "color": "d32ce6"}, {"type": "html", "value": "MP9 | Airlock", "color": "d32ce6"}, {"type": "html", "value": "Tec-9 | Fuel Injector", "color": "d32ce6"}, {"type": "html", "value": "AK-47 | Neon Revolution", "color": "eb4b4b"}, {"type": "html", "value": "FAMAS | Roll Cage", "color": "eb4b4b"}, {"type": "html", "value": "or an Exceedingly Rare Special Item!", "color": "ffd700"}, {"type": "html", "value": " "}, {"type": "html", "value": "", "color": "00a000", "app_data": {"limited": 1}}], "tags": [{"internal_name": "CSGO_Type_WeaponCase", "name": "Container", "category": "Type", "category_name": "Type"}, {"internal_name": "set_gamma_2", "name": "The Gamma 2 Collection", "category": "ItemSet", "category_name": "Collection"}, {"internal_name": "normal", "name": "Normal", "category": "Quality", "category_name": "Category"}, {"internal_name": "Rarity_Common", "name": "Base Grade", "category": "Rarity", "color": "b0c3d9", "category_name": "Quality"}]}, "310776711_302028390": {"appid": "730", "classid": "310776711", "instanceid": "302028390", "icon_url": "-9a81dlWLwJ2UUGcVs_nsVtzdOEdtWwKGZZLQHTxDZ7I56KU0Zwwo4NUX4oFJZEHLbXH5ApeO4YmlhxYQknCRvCo04DEVlxkKgpou7uifDhh3szdYz9D4uO6nYeDg7mgariClDMFusQh2LiTo9nw0FCw_UU6Y2ymdtOXclBtZl6B_AXolby-m9bi6yrTVV9L", "icon_url_large": "-9a81dlWLwJ2UUGcVs_nsVtzdOEdtWwKGZZLQHTxDZ7I56KU0Zwwo4NUX4oFJZEHLbXH5ApeO4YmlhxYQknCRvCo04DEVlxkKgpou7uifDhh3szdYz9D4uO6nYeDg8j4MqnWkyUFscYiiLGVp42l2gXm_UY5az2nIoDDcgNrMw3S-gftxui-g8Lq6M-Y1zI97ZLIVAoT", "icon_drag_url": "", "name": "MAG-7 | Metallic DDPAT", "market_hash_name": "MAG-7 | Metallic DDPAT (Factory New)", "market_name": "MAG-7 | Metallic DDPAT (Factory New)", "name_color": "D2D2D2", "background_color": "", "type": "Industrial Grade Shotgun", "tradable": 1, "marketable": 1, "commodity": 0, "market_tradable_restriction": "7", "descriptions": [{"type": "html", "value": "Exterior: Factory New"}, {"type": "html", "value": " "}, {"type": "html", "value": "The CT-exclusive Mag-7 delivers a devastating amount of damage at close range. Its rapid magazine-style reloads make it a great tactical choice. It has been painted using an urban Digital Disruptive Pattern (DDPAT) hydrographic over a metallic base coat."}, {"type": "html", "value": " "}, {"type": "html", "value": "The Train Collection", "color": "9da1a9", "app_data": {"def_index": "65535", "is_itemset_name": 1}}, {"type": "html", "value": " "}], "actions": [{"name": "Inspect in Game...", "link": "steam://rungame/730/76561202255233023/+csgo_econ_action_preview%20S%owner_steamid%A%assetid%D3325946442111629887"}], "market_actions": [{"name": "Inspect in Game...", "link": "steam://rungame/730/76561202255233023/+csgo_econ_action_preview%20M%listingid%A%assetid%D3325946442111629887"}], "tags": [{"internal_name": "CSGO_Type_Shotgun", "name": "Shotgun", "category": "Type", "category_name": "Type"}, {"internal_name": "weapon_mag7", "name": "MAG-7", "category": "Weapon", "category_name": "Weapon"}, {"internal_name": "set_train", "name": "The Train Collection", "category": "ItemSet", "category_name": "Collection"}, {"internal_name": "normal", "name": "Normal", "category": "Quality", "category_name": "Category"}, {"internal_name": "Rarity_Uncommon_Weapon", "name": "Industrial Grade", "category": "Rarity", "color": "5e98d9", "category_name": "Quality"}, {"internal_name": "WearCategory0", "name": "Factory New", "category": "Exterior", "category_name": "Exterior"}]}, "1690096482_0": {"appid": "730", "classid": "1690096482", "instanceid": "0", "icon_url": "-9a81dlWLwJ2UUGcVs_nsVtzdOEdtWwKGZZLQHTxDZ7I56KU0Zwwo4NUX4oFJZEHLbXU5A1PIYQNqhpOSV-fRPasw8rsUFJ5KBFZv668FFYynaSdJGhE74y0wNWIw_OlNuvXkDpSuZQmi--SrN-h3gey-Uo6YWmlIoCLMlhplhFFvwI", "icon_drag_url": "", "name": "Chroma 3 Case", "market_hash_name": "Chroma 3 Case", "market_name": "Chroma 3 Case", "name_color": "D2D2D2", "background_color": "", "type": "Base Grade Container", "tradable": 1, "marketable": 1, "commodity": 1, "market_tradable_restriction": "7", "market_buy_country_restriction": "FR", "descriptions": [{"type": "html", "value": " "}, {"type": "html", "value": "Container Series #141", "color": "99ccff"}, {"type": "html", "value": " "}, {"type": "html", "value": "Contains one of the following:"}, {"type": "html", "value": "Dual Berettas | Ventilators", "color": "4b69ff"}, {"type": "html", "value": "G3SG1 | Orange Crash", "color": "4b69ff"}, {"type": "html", "value": "M249 | Spectre", "color": "4b69ff"}, {"type": "html", "value": "MP9 | Bioleak", "color": "4b69ff"}, {"type": "html", "value": "P2000 | Oceanic", "color": "4b69ff"}, {"type": "html", "value": "Sawed-Off | Fubar", "color": "4b69ff"}, {"type": "html", "value": "SG 553 | Atlas", "color": "4b69ff"}, {"type": "html", "value": "CZ75-Auto | Red Astor", "color": "8847ff"}, {"type": "html", "value": "Galil AR | Firefight", "color": "8847ff"}, {"type": "html", "value": "SSG 08 | Ghost Crusader", "color": "8847ff"}, {"type": "html", "value": "Tec-9 | Re-Entry", "color": "8847ff"}, {"type": "html", "value": "XM1014 | Black Tie", "color": "8847ff"}, {"type": "html", "value": "AUG | Fleet Flock", "color": "d32ce6"}, {"type": "html", "value": "P250 | Asiimov", "color": "d32ce6"}, {"type": "html", "value": "UMP-45 | Primal Saber", "color": "d32ce6"}, {"type": "html", "value": "PP-Bizon | Judgement of Anubis", "color": "eb4b4b"}, {"type": "html", "value": "M4A1-S | Chantico's Fire", "color": "eb4b4b"}, {"type": "html", "value": "or an Exceedingly Rare Special Item!", "color": "ffd700"}, {"type": "html", "value": " "}, {"type": "html", "value": "", "color": "00a000", "app_data": {"limited": 1}}], "tags": [{"internal_name": "CSGO_Type_WeaponCase", "name": "Container", "category": "Type", "category_name": "Type"}, {"internal_name": "set_community_12", "name": "The Chroma 3 Collection", "category": "ItemSet", "category_name": "Collection"}, {"internal_name": "normal", "name": "Normal", "category": "Quality", "category_name": "Category"}, {"internal_name": "Rarity_Common", "name": "Base Grade", "category": "Rarity", "color": "b0c3d9", "category_name": "Quality"}]}, "310776765_302028390": {"appid": "730", "classid": "310776765", "instanceid": "302028390", "icon_url": "-9a81dlWLwJ2UUGcVs_nsVtzdOEdtWwKGZZLQHTxDZ7I56KU0Zwwo4NUX4oFJZEHLbXH5ApeO4YmlhxYQknCRvCo04DEVlxkKgpotLO_JAlfwOP3ZTxS6eOlnI-Zg8jhIbnQmFRc7cF4n-SPodjx2ALg-kppMG7xIYGUd1I8MlqG_VS7kLvo18Tq7szBzXJnuCVzsGGdwULIif0sOA", "icon_url_large": "-9a81dlWLwJ2UUGcVs_nsVtzdOEdtWwKGZZLQHTxDZ7I56KU0Zwwo4NUX4oFJZEHLbXH5ApeO4YmlhxYQknCRvCo04DEVlxkKgpotLO_JAlfwOP3ZTxS6eOlnI-Zg8jhIbnQmFRc7cF4n-T--Y3nj1H6_0c4Y2_3JY-QIQE8ZF_R_wW8kuy5gpO57cjOmyA16HEq4X_ZnRDm1AYMMLLoAlus5w", "icon_drag_url": "", "name": "PP-Bizon | Urban Dashed", "market_hash_name": "PP-Bizon | Urban Dashed (Field-Tested)", "market_name": "PP-Bizon | Urban Dashed (Field-Tested)", "name_color": "D2D2D2", "background_color": "", "type": "Consumer Grade SMG", "tradable": 1, "marketable": 1, "commodity": 0, "market_tradable_restriction": "7", "descriptions": [{"type": "html", "value": "Exterior: Field-Tested"}, {"type": "html", "value": " "}, {"type": "html", "value": "The Bizon SMG is low-damage, but offers a uniquely designed high-capacity drum magazine that reloads quickly. It has been spray-painted using short pieces of tape as stencils."}, {"type": "html", "value": " "}, {"type": "html", "value": "The Train Collection", "color": "9da1a9", "app_data": {"def_index": "65535", "is_itemset_name": 1}}, {"type": "html", "value": " "}], "actions": [{"name": "Inspect in Game...", "link": "steam://rungame/730/76561202255233023/+csgo_econ_action_preview%20S%owner_steamid%A%assetid%D210731060873518814"}], "market_actions": [{"name": "Inspect in Game...", "link": "steam://rungame/730/76561202255233023/+csgo_econ_action_preview%20M%listingid%A%assetid%D210731060873518814"}], "tags": [{"internal_name": "CSGO_Type_SMG", "name": "SMG", "category": "Type", "category_name": "Type"}, {"internal_name": "weapon_bizon", "name": "PP-Bizon", "category": "Weapon", "category_name": "Weapon"}, {"internal_name": "set_train", "name": "The Train Collection", "category": "ItemSet", "category_name": "Collection"}, {"internal_name": "normal", "name": "Normal", "category": "Quality", "category_name": "Category"}, {"internal_name": "Rarity_Common_Weapon", "name": "Consumer Grade", "category": "Rarity", "color": "b0c3d9", "category_name": "Quality"}, {"internal_name": "WearCategory2", "name": "Field-Tested", "category": "Exterior", "category_name": "Exterior"}]}, "2948874694_0": {"appid": "730", "classid": "2948874694", "instanceid": "0", "icon_url": "-9a81dlWLwJ2UUGcVs_nsVtzdOEdtWwKGZZLQHTxDZ7I56KU0Zwwo4NUX4oFJZEHLbXU5A1PIYQNqhpOSV-fRPasw8rsUFJ5KBFZv668FFUwnfbOdDgavYXukYTZkqf2ZbrTwmkE6scgj7CY94ml3FXl-ENkMW3wctOLMlhpVHKV9YA", "icon_drag_url": "", "name": "Horizon Case", "market_hash_name": "Horizon Case", "market_name": "Horizon Case", "name_color": "D2D2D2", "background_color": "", "type": "Base Grade Container", "tradable": 1, "marketable": 1, "commodity": 1, "market_tradable_restriction": "7", "market_buy_country_restriction": "FR", "descriptions": [{"type": "html", "value": " "}, {"type": "html", "value": "Container Series #244", "color": "99ccff"}, {"type": "html", "value": " "}, {"type": "html", "value": "Contains one of the following:"}, {"type": "html", "value": "AUG | Amber Slipstream", "color": "4b69ff"}, {"type": "html", "value": "Dual Berettas | Shred", "color": "4b69ff"}, {"type": "html", "value": "Glock-18 | Warhawk", "color": "4b69ff"}, {"type": "html", "value": "MP9 | Capillary", "color": "4b69ff"}, {"type": "html", "value": "P90 | Traction", "color": "4b69ff"}, {"type": "html", "value": "R8 Revolver | Survivalist", "color": "4b69ff"}, {"type": "html", "value": "Tec-9 | Snek-9", "color": "4b69ff"}, {"type": "html", "value": "CZ75-Auto | Eco", "color": "8847ff"}, {"type": "html", "value": "G3SG1 | High Seas", "color": "8847ff"}, {"type": "html", "value": "Nova | Toy Soldier", "color": "8847ff"}, {"type": "html", "value": "AWP | PAW", "color": "8847ff"}, {"type": "html", "value": "MP7 | Powercore", "color": "8847ff"}, {"type": "html", "value": "M4A1-S | Nightmare", "color": "d32ce6"}, {"type": "html", "value": "Sawed-Off | Devourer", "color": "d32ce6"}, {"type": "html", "value": "FAMAS | Eye of Athena", "color": "d32ce6"}, {"type": "html", "value": "AK-47 | Neon Rider", "color": "eb4b4b"}, {"type": "html", "value": "Desert Eagle | Code Red", "color": "eb4b4b"}, {"type": "html", "value": "or an Exceedingly Rare Special Item!", "color": "ffd700"}, {"type": "html", "value": " "}, {"type": "html", "value": "", "color": "00a000", "app_data": {"limited": 1}}], "tags": [{"internal_name": "CSGO_Type_WeaponCase", "name": "Container", "category": "Type", "category_name": "Type"}, {"internal_name": "set_community_20", "name": "The Horizon Collection", "category": "ItemSet", "category_name": "Collection"}, {"internal_name": "normal", "name": "Normal", "category": "Quality", "category_name": "Category"}, {"internal_name": "Rarity_Common", "name": "Base Grade", "category": "Rarity", "color": "b0c3d9", "category_name": "Quality"}]}, "1432174707_0": {"appid": "730", "classid": "1432174707", "instanceid": "0", "icon_url": "-9a81dlWLwJ2UUGcVs_nsVtzdOEdtWwKGZZLQHTxDZ7I56KU0Zwwo4NUX4oFJZEHLbXU5A1PIYQNqhpOSV-fRPasw8rsUFJ5KBFZv668FFYwnfKfcG9HvN7iktaOkqD1auLTxD5SvZYgiLvFpo7xjVLh-kdrYWnzcoGLMlhpsyM-5vg", "icon_drag_url": "", "name": "Revolver Case", "market_hash_name": "Revolver Case", "market_name": "Revolver Case", "name_color": "D2D2D2", "background_color": "", "type": "Base Grade Container", "tradable": 1, "marketable": 1, "commodity": 1, "market_tradable_restriction": "7", "market_buy_country_restriction": "FR", "descriptions": [{"type": "html", "value": " "}, {"type": "html", "value": "Container Series #111", "color": "99ccff"}, {"type": "html", "value": " "}, {"type": "html", "value": "Contains one of the following:"}, {"type": "html", "value": "R8 Revolver | Crimson Web", "color": "4b69ff"}, {"type": "html", "value": "AUG | Ricochet", "color": "4b69ff"}, {"type": "html", "value": "Desert Eagle | Corinthian", "color": "4b69ff"}, {"type": "html", "value": "P2000 | Imperial", "color": "4b69ff"}, {"type": "html", "value": "Sawed-Off | Yorick", "color": "4b69ff"}, {"type": "html", "value": "SCAR-20 | Outbreak", "color": "4b69ff"}, {"type": "html", "value": "PP-Bizon | Fuel Rod", "color": "8847ff"}, {"type": "html", "value": "Five-SeveN | Retrobution", "color": "8847ff"}, {"type": "html", "value": "Negev | Power Loader", "color": "8847ff"}, {"type": "html", "value": "SG 553 | Tiger Moth", "color": "8847ff"}, {"type": "html", "value": "Tec-9 | Avalanche", "color": "8847ff"}, {"type": "html", "value": "XM1014 | Teclu Burner", "color": "8847ff"}, {"type": "html", "value": "AK-47 | Point Disarray", "color": "d32ce6"}, {"type": "html", "value": "G3SG1 | The Executioner", "color": "d32ce6"}, {"type": "html", "value": "P90 | Shapewood", "color": "d32ce6"}, {"type": "html", "value": "M4A4 | Royal Paladin", "color": "eb4b4b"}, {"type": "html", "value": "R8 Revolver | Fade", "color": "eb4b4b"}, {"type": "html", "value": "or an Exceedingly Rare Special Item!", "color": "ffd700"}, {"type": "html", "value": " "}, {"type": "html", "value": "", "color": "00a000", "app_data": {"limited": 1}}], "tags": [{"internal_name": "CSGO_Type_WeaponCase", "name": "Container", "category": "Type", "category_name": "Type"}, {"internal_name": "set_community_10", "name": "The Revolver Case Collection", "category": "ItemSet", "category_name": "Collection"}, {"internal_name": "normal", "name": "Normal", "category": "Quality", "category_name": "Category"}, {"internal_name": "Rarity_Common", "name": "Base Grade", "category": "Rarity", "color": "b0c3d9", "category_name": "Quality"}]}, "1989287937_302028390": {"appid": "730", "classid": "1989287937", "instanceid": "302028390", "icon_url": "IzMF03bi9WpSBq-S-ekoE33L-iLqGFHVaU25ZzQNQcXdB2ozio1RrlIWFK3UfvMYB8UsvjiMXojflsZalyxSh31CIyHz2GZ-KuFpPsrTzBG0pO-CI3DyeyfFJjOXS1s9SOJZZ2rb9zXx5OrAFjDOE-1_R1pQKaNW8TUbOs-LPxJo1I8JqiuomUM7HRkkfddLZQOvw2QfKOBykHgWcJhPkVn5Kw", "icon_url_large": "IzMF03bi9WpSBq-S-ekoE33L-iLqGFHVaU25ZzQNQcXdB2ozio1RrlIWFK3UfvMYB8UsvjiMXojflsZalyxSh31CIyHz2GZ-KuFpPsrTzBG0pO-CI3DyeyfFJjPmEF96GuZAMTuMrTGktOuSF2qcE70sRA4NKaJQo2IdOpqAaUQ-0oNY_TPok0d4S1g4fMIAcwC3xWYeJLExwTEePJZVkS2kI5cvBshUiw", "icon_drag_url": "", "name": "Sealed Graffiti | QQ (Battle Green)", "market_hash_name": "Sealed Graffiti | QQ (Battle Green)", "market_name": "Sealed Graffiti | QQ (Battle Green)", "name_color": "D2D2D2", "background_color": "", "type": "Base Grade Graffiti", "tradable": 1, "marketable": 1, "commodity": 1, "market_tradable_restriction": "7", "descriptions": [{"type": "html", "value": "This is a sealed container of a graffiti pattern. Once this graffiti pattern is unsealed, it will provide you with enough charges to apply the graffiti pattern <b>50</b> times to the in-game world."}, {"type": "html", "value": " "}, {"type": "html", "value": "", "color": "00a000", "app_data": {"limited": 1}}], "actions": [{"name": "Inspect in Game...", "link": "steam://rungame/730/76561202255233023/+csgo_econ_action_preview%20S%owner_steamid%A%assetid%D9685555088655648748"}], "market_actions": [{"name": "Inspect in Game...", "link": "steam://rungame/730/76561202255233023/+csgo_econ_action_preview%20M%listingid%A%assetid%D9685555088655648748"}], "tags": [{"internal_name": "CSGO_Type_Spray", "name": "Graffiti", "category": "Type", "category_name": "Type"}, {"internal_name": "normal", "name": "Normal", "category": "Quality", "category_name": "Category"}, {"internal_name": "Rarity_Common", "name": "Base Grade", "category": "Rarity", "color": "b0c3d9", "category_name": "Quality"}, {"internal_name": "Tint7", "name": "Battle Green", "category": "SprayColorCategory", "category_name": "Graffiti Color"}]}, "1989281736_302028390": {"appid": "730", "classid": "1989281736", "instanceid": "302028390", "icon_url": "IzMF03bi9WpSBq-S-ekoE33L-iLqGFHVaU25ZzQNQcXdB2ozio1RrlIWFK3UfvMYB8UsvjiMXojflsZalyxSh31CIyHz2GZ-KuFpPsrTzBG0pPSEEEvycTKKfXSJTA88RLBYZm_d-Df2s7udQ2ydQLl5S18FL_BSp2wca8vca0E5hZlLpWL-lEtxEQQlZ8lSeR-30ylKNehznyD_8PAlXw", "icon_url_large": "IzMF03bi9WpSBq-S-ekoE33L-iLqGFHVaU25ZzQNQcXdB2ozio1RrlIWFK3UfvMYB8UsvjiMXojflsZalyxSh31CIyHz2GZ-KuFpPsrTzBG0pPSEEEvycTL7IyDLG1smRLBfZDvRr2ejs7iWRTDJF-h4FQpQKKsC8GZLaZ-IbBA-hYUJrjbvxAptEBFuccpKfx2233gHOK0p0XxLIZ5UnnUlo9Zlxw", "icon_drag_url": "", "name": "Sealed Graffiti | Rage Mode (Princess Pink)", "market_hash_name": "Sealed Graffiti | Rage Mode (Princess Pink)", "market_name": "Sealed Graffiti | Rage Mode (Princess Pink)", "name_color": "D2D2D2", "background_color": "", "type": "Base Grade Graffiti", "tradable": 1, "marketable": 1, "commodity": 1, "market_tradable_restriction": "7", "descriptions": [{"type": "html", "value": "This is a sealed container of a graffiti pattern. Once this graffiti pattern is unsealed, it will provide you with enough charges to apply the graffiti pattern <b>50</b> times to the in-game world."}, {"type": "html", "value": " "}, {"type": "html", "value": "", "color": "00a000", "app_data": {"limited": 1}}], "actions": [{"name": "Inspect in Game...", "link": "steam://rungame/730/76561202255233023/+csgo_econ_action_preview%20S%owner_steamid%A%assetid%D4938763967477721384"}], "market_actions": [{"name": "Inspect in Game...", "link": "steam://rungame/730/76561202255233023/+csgo_econ_action_preview%20M%listingid%A%assetid%D4938763967477721384"}], "tags": [{"internal_name": "CSGO_Type_Spray", "name": "Graffiti", "category": "Type", "category_name": "Type"}, {"internal_name": "normal", "name": "Normal", "category": "Quality", "category_name": "Category"}, {"internal_name": "Rarity_Common", "name": "Base Grade", "category": "Rarity", "color": "b0c3d9", "category_name": "Quality"}, {"internal_name": "Tint17", "name": "Princess Pink", "category": "SprayColorCategory", "category_name": "Graffiti Color"}]}, "1797256701_0": {"appid": "730", "classid": "1797256701", "instanceid": "0", "icon_url": "-9a81dlWLwJ2UUGcVs_nsVtzdOEdtWwKGZZLQHTxDZ7I56KU0Zwwo4NUX4oFJZEHLbXU5A1PIYQNqhpOSV-fRPasw8rsUFJ5KBFZv668FFYznarJJjkQ6ovjw4SPlfP3auqEl2oBuJB1j--WoY322QziqkdpZGr3IteLMlhpw4RJCv8", "icon_drag_url": "", "name": "Gamma Case", "market_hash_name": "Gamma Case", "market_name": "Gamma Case", "name_color": "D2D2D2", "background_color": "", "type": "Base Grade Container", "tradable": 1, "marketable": 1, "commodity": 1, "market_tradable_restriction": "7", "market_buy_country_restriction": "FR", "descriptions": [{"type": "html", "value": " "}, {"type": "html", "value": "Container Series #144", "color": "99ccff"}, {"type": "html", "value": " "}, {"type": "html", "value": "Contains one of the following:"}, {"type": "html", "value": "Five-SeveN | Violent Daimyo", "color": "4b69ff"}, {"type": "html", "value": "MAC-10 | Carnivore", "color": "4b69ff"}, {"type": "html", "value": "Nova | Exo", "color": "4b69ff"}, {"type": "html", "value": "P250 | Iron Clad", "color": "4b69ff"}, {"type": "html", "value": "PP-Bizon | Harvester", "color": "4b69ff"}, {"type": "html", "value": "SG 553 | Aerial", "color": "4b69ff"}, {"type": "html", "value": "Tec-9 | Ice Cap", "color": "4b69ff"}, {"type": "html", "value": "AUG | Aristocrat", "color": "8847ff"}, {"type": "html", "value": "AWP | Phobos", "color": "8847ff"}, {"type": "html", "value": "P90 | Chopper", "color": "8847ff"}, {"type": "html", "value": "R8 Revolver | Reboot", "color": "8847ff"}, {"type": "html", "value": "Sawed-Off | Limelight", "color": "8847ff"}, {"type": "html", "value": "M4A4 | Desolate Space", "color": "d32ce6"}, {"type": "html", "value": "P2000 | Imperial Dragon", "color": "d32ce6"}, {"type": "html", "value": "SCAR-20 | Bloodsport", "color": "d32ce6"}, {"type": "html", "value": "Glock-18 | Wasteland Rebel", "color": "eb4b4b"}, {"type": "html", "value": "M4A1-S | Mecha Industries", "color": "eb4b4b"}, {"type": "html", "value": "or an Exceedingly Rare Special Item!", "color": "ffd700"}, {"type": "html", "value": " "}, {"type": "html", "value": "", "color": "00a000", "app_data": {"limited": 1}}], "tags": [{"internal_name": "CSGO_Type_WeaponCase", "name": "Container", "category": "Type", "category_name": "Type"}, {"internal_name": "set_community_13", "name": "The Gamma Collection", "category": "ItemSet", "category_name": "Collection"}, {"internal_name": "normal", "name": "Normal", "category": "Quality", "category_name": "Category"}, {"internal_name": "Rarity_Common", "name": "Base Grade", "category": "Rarity", "color": "b0c3d9", "category_name": "Quality"}]}, "310820898_302028390": {"appid": "730", "classid": "310820898", "instanceid": "302028390", "icon_url": "-9a81dlWLwJ2UUGcVs_nsVtzdOEdtWwKGZZLQHTxDZ7I56KU0Zwwo4NUX4oFJZEHLbXH5ApeO4YmlhxYQknCRvCo04DEVlxkKgpouLWzKjhzw8zSdD9Q7d-3mb-HnvD8J_WFlzoC6sFy3u_Apo6gi1Djr0tlMGGgd46WdQY-NVuB-1K9w-i-g8W_ot2XnqyWhAHr", "icon_url_large": "-9a81dlWLwJ2UUGcVs_nsVtzdOEdtWwKGZZLQHTxDZ7I56KU0Zwwo4NUX4oFJZEHLbXH5ApeO4YmlhxYQknCRvCo04DEVlxkKgpouLWzKjhzw8zSdD9Q7d-3mb-HnvD8J4Tdl3lW7Ysli7iS94j23FK1-BFpMD30cI6cIQ5tMlDT_VG-le2-hJW_vpuYzyFgpGB8smlospdV", "icon_drag_url": "", "name": "Nova | Predator", "market_hash_name": "Nova | Predator (Factory New)", "market_name": "Nova | Predator (Factory New)", "name_color": "D2D2D2", "background_color": "", "type": "Consumer Grade Shotgun", "tradable": 1, "marketable": 1, "commodity": 0, "market_tradable_restriction": "7", "descriptions": [{"type": "html", "value": "Exterior: Factory New"}, {"type": "html", "value": " "}, {"type": "html", "value": "The Nova's rock-bottom price tag makes it a great ambush weapon for a cash-strapped team. It has been spray-painted in a zebra stripe pattern."}, {"type": "html", "value": " "}, {"type": "html", "value": "The Dust 2 Collection", "color": "9da1a9", "app_data": {"def_index": "65535", "is_itemset_name": 1}}, {"type": "html", "value": " "}], "actions": [{"name": "Inspect in Game...", "link": "steam://rungame/730/76561202255233023/+csgo_econ_action_preview%20S%owner_steamid%A%assetid%D10245280437347188955"}], "market_actions": [{"name": "Inspect in Game...", "link": "steam://rungame/730/76561202255233023/+csgo_econ_action_preview%20M%listingid%A%assetid%D10245280437347188955"}], "tags": [{"internal_name": "CSGO_Type_Shotgun", "name": "Shotgun", "category": "Type", "category_name": "Type"}, {"internal_name": "weapon_nova", "name": "Nova", "category": "Weapon", "category_name": "Weapon"}, {"internal_name": "set_dust_2", "name": "The Dust 2 Collection", "category": "ItemSet", "category_name": "Collection"}, {"internal_name": "normal", "name": "Normal", "category": "Quality", "category_name": "Category"}, {"internal_name": "Rarity_Common_Weapon", "name": "Consumer Grade", "category": "Rarity", "color": "b0c3d9", "category_name": "Quality"}, {"internal_name": "WearCategory0", "name": "Factory New", "category": "Exterior", "category_name": "Exterior"}]}, "469443670_302028390": {"appid": "730", "classid": "469443670", "instanceid": "302028390", "icon_url": "-9a81dlWLwJ2UUGcVs_nsVtzdOEdtWwKGZZLQHTxDZ7I56KU0Zwwo4NUX4oFJZEHLbXH5ApeO4YmlhxYQknCRvCo04DEVlxkKgpou7umeldf0v33YjRO-tmkq4yCkP_gfeiBzjlUsZRz0-_F8Y7xjFftqURuNzj3IIWdcFBrYAyFrFG-l7_q08ei_MOeOloUkcI", "icon_url_large": "-9a81dlWLwJ2UUGcVs_nsVtzdOEdtWwKGZZLQHTxDZ7I56KU0Zwwo4NUX4oFJZEHLbXH5ApeO4YmlhxYQknCRvCo04DEVlxkKgpou7umeldf0v33YjRO-tmkq4yCkP_gDLfQhGxUppYh0rvErN330VKwrxE4Nzr6doGXJlc6ZVvY-AfrwLq605a86szMnyN9-n51V6p-9aU", "icon_drag_url": "", "name": "MAC-10 | Silver", "market_hash_name": "MAC-10 | Silver (Factory New)", "market_name": "MAC-10 | Silver (Factory New)", "name_color": "D2D2D2", "background_color": "", "type": "Industrial Grade SMG", "tradable": 1, "marketable": 1, "commodity": 0, "market_tradable_restriction": "7", "descriptions": [{"type": "html", "value": "Exterior: Factory New"}, {"type": "html", "value": " "}, {"type": "html", "value": "Essentially a box that bullets come out of, the MAC-10 SMG boasts a high rate of fire, with poor spread accuracy and high recoil as trade-offs. It has been painted with a chrome base coat and candied in transparent silver anodized effect paint.\n\n<i>There is beauty in simplicity - Franz Kriegeld, Phoenix Tactician</i>"}, {"type": "html", "value": " "}, {"type": "html", "value": "The Bank Collection", "color": "9da1a9", "app_data": {"def_index": "65535", "is_itemset_name": 1}}, {"type": "html", "value": " "}], "actions": [{"name": "Inspect in Game...", "link": "steam://rungame/730/76561202255233023/+csgo_econ_action_preview%20S%owner_steamid%A%assetid%D9523989832839021633"}], "market_actions": [{"name": "Inspect in Game...", "link": "steam://rungame/730/76561202255233023/+csgo_econ_action_preview%20M%listingid%A%assetid%D9523989832839021633"}], "tags": [{"internal_name": "CSGO_Type_SMG", "name": "SMG", "category": "Type", "category_name": "Type"}, {"internal_name": "weapon_mac10", "name": "MAC-10", "category": "Weapon", "category_name": "Weapon"}, {"internal_name": "set_bank", "name": "The Bank Collection", "category": "ItemSet", "category_name": "Collection"}, {"internal_name": "normal", "name": "Normal", "category": "Quality", "category_name": "Category"}, {"internal_name": "Rarity_Uncommon_Weapon", "name": "Industrial Grade", "category": "Rarity", "color": "5e98d9", "category_name": "Quality"}, {"internal_name": "WearCategory0", "name": "Factory New", "category": "Exterior", "category_name": "Exterior"}]}, "310779639_302028390": {"appid": "730", "classid": "310779639", "instanceid": "302028390", "icon_url": "-9a81dlWLwJ2UUGcVs_nsVtzdOEdtWwKGZZLQHTxDZ7I56KU0Zwwo4NUX4oFJZEHLbXH5ApeO4YmlhxYQknCRvCo04DEVlxkKgpopbmkOVUw7ODHTi1P7-O-kYGdjrmsYeOCxDJUupEi3-3A892h2FHgrRdrZDv1Jo6ccwU2Yl3T81Tqx-jrm9bi6xwIv_x-", "icon_url_large": "-9a81dlWLwJ2UUGcVs_nsVtzdOEdtWwKGZZLQHTxDZ7I56KU0Zwwo4NUX4oFJZEHLbXH5ApeO4YmlhxYQknCRvCo04DEVlxkKgpopbmkOVUw7ODHTi1P7-O-kYGdjsj4MqnWkyUJup0i2LDEp9im3VC1rUJoYzz3ctKSdVQ4Y1DZ-1K2wuvsjJPoupvN1zI97UzteTlX", "icon_drag_url": "", "name": "SCAR-20 | Contractor", "market_hash_name": "SCAR-20 | Contractor (Battle-Scarred)", "market_name": "SCAR-20 | Contractor (Battle-Scarred)", "name_color": "D2D2D2", "background_color": "", "type": "Consumer Grade Sniper Rifle", "tradable": 1, "marketable": 1, "commodity": 0, "market_tradable_restriction": "7", "descriptions": [{"type": "html", "value": "Exterior: Battle-Scarred"}, {"type": "html", "value": " "}, {"type": "html", "value": "The SCAR-20 is a semi-automatic sniper rifle that trades a high rate of fire and powerful long-distance damage for sluggish movement speed and big price tag. It has individual parts spray-painted tan, navy and dark green.\n\n<i>Rona Sabri still hasn't forgiven Sebastien for not selecting her to go after Turner</i>"}, {"type": "html", "value": " "}, {"type": "html", "value": "The Safehouse Collection", "color": "9da1a9", "app_data": {"def_index": "65535", "is_itemset_name": 1}}, {"type": "html", "value": " "}], "actions": [{"name": "Inspect in Game...", "link": "steam://rungame/730/76561202255233023/+csgo_econ_action_preview%20S%owner_steamid%A%assetid%D9984168586336929624"}], "market_actions": [{"name": "Inspect in Game...", "link": "steam://rungame/730/76561202255233023/+csgo_econ_action_preview%20M%listingid%A%assetid%D9984168586336929624"}], "tags": [{"internal_name": "CSGO_Type_SniperRifle", "name": "Sniper Rifle", "category": "Type", "category_name": "Type"}, {"internal_name": "weapon_scar20", "name": "SCAR-20", "category": "Weapon", "category_name": "Weapon"}, {"internal_name": "set_safehouse", "name": "The Safehouse Collection", "category": "ItemSet", "category_name": "Collection"}, {"internal_name": "normal", "name": "Normal", "category": "Quality", "category_name": "Category"}, {"internal_name": "Rarity_Common_Weapon", "name": "Consumer Grade", "category": "Rarity", "color": "b0c3d9", "category_name": "Quality"}, {"internal_name": "WearCategory4", "name": "Battle-Scarred", "category": "Exterior", "category_name": "Exterior"}]}, "2521767801_0": {"appid": "730", "classid": "2521767801", "instanceid": "0", "icon_url": "-9a81dlWLwJ2UUGcVs_nsVtzdOEdtWwKGZZLQHTxDZ7I56KU0Zwwo4NUX4oFJZEHLbXU5A1PIYQNqhpOSV-fRPasw8rsUFJ5KBFZv668FFY4naeaJGhGtdnmx4Tek_bwY-iFlGlUsJMp3LuTot-mjFGxqUttZ2r3d4eLMlhpnZPxZK0", "icon_drag_url": "", "name": "Spectrum 2 Case", "market_hash_name": "Spectrum 2 Case", "market_name": "Spectrum 2 Case", "name_color": "D2D2D2", "background_color": "", "type": "Base Grade Container", "tradable": 1, "marketable": 1, "commodity": 1, "market_tradable_restriction": "7", "market_buy_country_restriction": "FR", "descriptions": [{"type": "html", "value": " "}, {"type": "html", "value": "Container Series #220", "color": "99ccff"}, {"type": "html", "value": " "}, {"type": "html", "value": "Contains one of the following:"}, {"type": "html", "value": "Sawed-Off | Morris", "color": "4b69ff"}, {"type": "html", "value": "AUG | Triqua", "color": "4b69ff"}, {"type": "html", "value": "G3SG1 | Hunter", "color": "4b69ff"}, {"type": "html", "value": "Glock-18 | Off World", "color": "4b69ff"}, {"type": "html", "value": "MAC-10 | Oceanic", "color": "4b69ff"}, {"type": "html", "value": "Tec-9 | Cracked Opal", "color": "4b69ff"}, {"type": "html", "value": "SCAR-20 | Jungle Slipstream", "color": "4b69ff"}, {"type": "html", "value": "MP9 | Goo", "color": "8847ff"}, {"type": "html", "value": "SG 553 | Phantom", "color": "8847ff"}, {"type": "html", "value": "CZ75-Auto | Tacticat", "color": "8847ff"}, {"type": "html", "value": "UMP-45 | Exposure", "color": "8847ff"}, {"type": "html", "value": "XM1014 | Ziggy", "color": "8847ff"}, {"type": "html", "value": "PP-Bizon | High Roller", "color": "d32ce6"}, {"type": "html", "value": "M4A1-S | Leaded Glass", "color": "d32ce6"}, {"type": "html", "value": "R8 Revolver | Llama Cannon", "color": "d32ce6"}, {"type": "html", "value": "AK-47 | The Empress", "color": "eb4b4b"}, {"type": "html", "value": "P250 | See Ya Later", "color": "eb4b4b"}, {"type": "html", "value": "or an Exceedingly Rare Special Item!", "color": "ffd700"}, {"type": "html", "value": " "}, {"type": "html", "value": "", "color": "00a000", "app_data": {"limited": 1}}], "tags": [{"internal_name": "CSGO_Type_WeaponCase", "name": "Container", "category": "Type", "category_name": "Type"}, {"internal_name": "set_community_18", "name": "The Spectrum 2 Collection", "category": "ItemSet", "category_name": "Collection"}, {"internal_name": "normal", "name": "Normal", "category": "Quality", "category_name": "Category"}, {"internal_name": "Rarity_Common", "name": "Base Grade", "category": "Rarity", "color": "b0c3d9", "category_name": "Quality"}]}, "1989302515_302028390": {"appid": "730", "classid": "1989302515", "instanceid": "302028390", "icon_url": "IzMF03bi9WpSBq-S-ekoE33L-iLqGFHVaU25ZzQNQcXdB2ozio1RrlIWFK3UfvMYB8UsvjiMXojflsZalyxSh31CIyHz2GZ-KuFpPsrTzBG0qeODGEv7ZyTBPW-LSl1rSeJZN27f-TGgtrvBE27KReEuFlhRf6QB8mBANZvdPBJr1dNf5XW2kAJ-ERonYMhTfBuy2ngKbOkgnycTfMrDip3T", "icon_url_large": "IzMF03bi9WpSBq-S-ekoE33L-iLqGFHVaU25ZzQNQcXdB2ozio1RrlIWFK3UfvMYB8UsvjiMXojflsZalyxSh31CIyHz2GZ-KuFpPsrTzBG0qeODGEv7ZyTBPR7VHUxvGK1dNG_Y_Tei7OuVFz2cSOAsQQ8EevcMo20aacjfPxQ10oENqDXpkxMlUAYmdYNFfwO02HkGPaks2C0LeJ8HnnKhLyb804cr", "icon_drag_url": "", "name": "Sealed Graffiti | Loser (Monarch Blue)", "market_hash_name": "Sealed Graffiti | Loser (Monarch Blue)", "market_name": "Sealed Graffiti | Loser (Monarch Blue)", "name_color": "D2D2D2", "background_color": "", "type": "Base Grade Graffiti", "tradable": 1, "marketable": 1, "commodity": 1, "market_tradable_restriction": "7", "descriptions": [{"type": "html", "value": "This is a sealed container of a graffiti pattern. Once this graffiti pattern is unsealed, it will provide you with enough charges to apply the graffiti pattern <b>50</b> times to the in-game world."}, {"type": "html", "value": " "}, {"type": "html", "value": "", "color": "00a000", "app_data": {"limited": 1}}], "actions": [{"name": "Inspect in Game...", "link": "steam://rungame/730/76561202255233023/+csgo_econ_action_preview%20S%owner_steamid%A%assetid%D5486063755765114286"}], "market_actions": [{"name": "Inspect in Game...", "link": "steam://rungame/730/76561202255233023/+csgo_econ_action_preview%20M%listingid%A%assetid%D5486063755765114286"}], "tags": [{"internal_name": "CSGO_Type_Spray", "name": "Graffiti", "category": "Type", "category_name": "Type"}, {"internal_name": "normal", "name": "Normal", "category": "Quality", "category_name": "Category"}, {"internal_name": "Rarity_Common", "name": "Base Grade", "category": "Rarity", "color": "b0c3d9", "category_name": "Quality"}, {"internal_name": "Tint12", "name": "Monarch Blue", "category": "SprayColorCategory", "category_name": "Graffiti Color"}]}, "1989295965_302028390": {"appid": "730", "classid": "1989295965", "instanceid": "302028390", "icon_url": "IzMF03bi9WpSBq-S-ekoE33L-iLqGFHVaU25ZzQNQcXdB2ozio1RrlIWFK3UfvMYB8UsvjiMXojflsZalyxSh31CIyHz2GZ-KuFpPsrTzBG0pPuIHnX7ZHmWfCXbTg4-H7FfNmmKqGKgsO-dEW3MQe0pQF0BeaQC9jJKP86ObhZoysdVrCO7mEhyDBs9ftFPYAOil3UWae52zDtN8SdI", "icon_url_large": "IzMF03bi9WpSBq-S-ekoE33L-iLqGFHVaU25ZzQNQcXdB2ozio1RrlIWFK3UfvMYB8UsvjiMXojflsZalyxSh31CIyHz2GZ-KuFpPsrTzBG0pPuIHnX7ZAjILjPeGRBsTuZYN2iM-mHwt7-cFjvOQOB4EloAfaRX8DcdPsjdaRBohoADr2fg2VRzGVArfclJYgKuxmAaIbE8lSAXfZhRzUXpu3bq", "icon_drag_url": "", "name": "Sealed Graffiti | Eye Spy (Desert Amber)", "market_hash_name": "Sealed Graffiti | Eye Spy (Desert Amber)", "market_name": "Sealed Graffiti | Eye Spy (Desert Amber)", "name_color": "D2D2D2", "background_color": "", "type": "Base Grade Graffiti", "tradable": 1, "marketable": 1, "commodity": 1, "market_tradable_restriction": "7", "descriptions": [{"type": "html", "value": "This is a sealed container of a graffiti pattern. Once this graffiti pattern is unsealed, it will provide you with enough charges to apply the graffiti pattern <b>50</b> times to the in-game world."}, {"type": "html", "value": " "}, {"type": "html", "value": "", "color": "00a000", "app_data": {"limited": 1}}], "actions": [{"name": "Inspect in Game...", "link": "steam://rungame/730/76561202255233023/+csgo_econ_action_preview%20S%owner_steamid%A%assetid%D16321154044671182660"}], "market_actions": [{"name": "Inspect in Game...", "link": "steam://rungame/730/76561202255233023/+csgo_econ_action_preview%20M%listingid%A%assetid%D16321154044671182660"}], "tags": [{"internal_name": "CSGO_Type_Spray", "name": "Graffiti", "category": "Type", "category_name": "Type"}, {"internal_name": "normal", "name": "Normal", "category": "Quality", "category_name": "Category"}, {"internal_name": "Rarity_Common", "name": "Base Grade", "category": "Rarity", "color": "b0c3d9", "category_name": "Quality"}, {"internal_name": "Tint5", "name": "Desert Amber", "category": "SprayColorCategory", "category_name": "Graffiti Color"}]}, "2066632015_0": {"appid": "730", "classid": "2066632015", "instanceid": "0", "icon_url": "-9a81dlWLwJ2UUGcVs_nsVtzdOEdtWwKGZZLQHTxDZ7I56KU0Zwwo4NUX4oFJZEHLbXU5A1PIYQNqhpOSV-fRPasw8rsUFJ5KBFZv668FFY1naTMdzwTtNrukteIkqT2MO_Uwz5Q6cYhibyXo4rw2ALsrkRoYjuncNCLMlhpEV4XDTk", "icon_drag_url": "", "name": "Glove Case", "market_hash_name": "Glove Case", "market_name": "Glove Case", "name_color": "D2D2D2", "background_color": "", "type": "Base Grade Container", "tradable": 1, "marketable": 1, "commodity": 1, "market_tradable_restriction": "7", "market_buy_country_restriction": "FR", "descriptions": [{"type": "html", "value": " "}, {"type": "html", "value": "Container Series #179", "color": "99ccff"}, {"type": "html", "value": " "}, {"type": "html", "value": "Contains one of the following:"}, {"type": "html", "value": "CZ75-Auto | Polymer", "color": "4b69ff"}, {"type": "html", "value": "Glock-18 | Ironwork", "color": "4b69ff"}, {"type": "html", "value": "MP7 | Cirrus", "color": "4b69ff"}, {"type": "html", "value": "Galil AR | Black Sand", "color": "4b69ff"}, {"type": "html", "value": "MP9 | Sand Scale", "color": "4b69ff"}, {"type": "html", "value": "MAG-7 | Sonar", "color": "4b69ff"}, {"type": "html", "value": "P2000 | Turf", "color": "4b69ff"}, {"type": "html", "value": "Dual Berettas | Royal Consorts", "color": "8847ff"}, {"type": "html", "value": "G3SG1 | Stinger", "color": "8847ff"}, {"type": "html", "value": "M4A1-S | Flashback", "color": "8847ff"}, {"type": "html", "value": "Nova | Gila", "color": "8847ff"}, {"type": "html", "value": "USP-S | Cyrex", "color": "8847ff"}, {"type": "html", "value": "FAMAS | Mecha Industries", "color": "d32ce6"}, {"type": "html", "value": "P90 | Shallow Grave", "color": "d32ce6"}, {"type": "html", "value": "Sawed-Off | Wasteland Princess", "color": "d32ce6"}, {"type": "html", "value": "SSG 08 | Dragonfire", "color": "eb4b4b"}, {"type": "html", "value": "M4A4 | Buzz Kill", "color": "eb4b4b"}, {"type": "html", "value": "or the Exceedingly Rare Gloves!", "color": "ffd700"}, {"type": "html", "value": " "}, {"type": "html", "value": "", "color": "00a000", "app_data": {"limited": 1}}], "tags": [{"internal_name": "CSGO_Type_WeaponCase", "name": "Container", "category": "Type", "category_name": "Type"}, {"internal_name": "set_community_15", "name": "The Glove Collection", "category": "ItemSet", "category_name": "Collection"}, {"internal_name": "normal", "name": "Normal", "category": "Quality", "category_name": "Category"}, {"internal_name": "Rarity_Common", "name": "Base Grade", "category": "Rarity", "color": "b0c3d9", "category_name": "Quality"}]}, "1989273941_302028390": {"appid": "730", "classid": "1989273941", "instanceid": "302028390", "icon_url": "IzMF03bi9WpSBq-S-ekoE33L-iLqGFHVaU25ZzQNQcXdB2ozio1RrlIWFK3UfvMYB8UsvjiMXojflsZalyxSh31CIyHz2GZ-KuFpPsrTzBG0oPqID0v0ejjXPCTdUlg_RbNeZ2GK-WGnsb_BQTzIF7t6RQwEfaAN-mBMbs2KPBZv0NMCrjH2h0p6WBUnfspUfRq33n0DPaR4n3lLIZ5R_Daz1_A", "icon_url_large": "IzMF03bi9WpSBq-S-ekoE33L-iLqGFHVaU25ZzQNQcXdB2ozio1RrlIWFK3UfvMYB8UsvjiMXojflsZalyxSh31CIyHz2GZ-KuFpPsrTzBG0oPqID0v0ejjXPCTdI1JpD-QLK2yKqjP05-6TQG7MQL4pRQsDKKFX9WcaP5jYbRc03IYJrmS-whAsHU9mYstBNgy0xnsBPKgp3CgCKdJfniz5cpHafYu3OIc", "icon_drag_url": "", "name": "Graffiti | X-Axes (Battle Green)", "market_hash_name": "Graffiti | X-Axes (Battle Green)", "market_name": "Graffiti | X-Axes (Battle Green)", "name_color": "D2D2D2", "background_color": "", "type": "Base Grade Graffiti", "tradable": 0, "marketable": 0, "commodity": 1, "market_tradable_restriction": "7", "descriptions": [{"type": "html", "value": "This graffiti can be applied to the in-game world. You can apply it until you run out of charges."}, {"type": "html", "value": " "}, {"type": "html", "value": "", "color": "00a000", "app_data": {"limited": 1}}, {"type": "html", "value": " "}, {"type": "html", "value": ""}], "actions": [{"name": "Inspect in Game...", "link": "steam://rungame/730/76561202255233023/+csgo_econ_action_preview%20S%owner_steamid%A%assetid%D17051198977522978789"}], "market_actions": [{"name": "Inspect in Game...", "link": "steam://rungame/730/76561202255233023/+csgo_econ_action_preview%20M%listingid%A%assetid%D17051198977522978789"}], "tags": [{"internal_name": "CSGO_Type_Spray", "name": "Graffiti", "category": "Type", "category_name": "Type"}, {"internal_name": "normal", "name": "Normal", "category": "Quality", "category_name": "Category"}, {"internal_name": "Rarity_Common", "name": "Base Grade", "category": "Rarity", "color": "b0c3d9", "category_name": "Quality"}, {"internal_name": "Tint7", "name": "Battle Green", "category": "SprayColorCategory", "category_name": "Graffiti Color"}]}, "1989274855_302028390": {"appid": "730", "classid": "1989274855", "instanceid": "302028390", "icon_url": "IzMF03bi9WpSBq-S-ekoE33L-iLqGFHVaU25ZzQNQcXdB2ozio1RrlIWFK3UfvMYB8UsvjiMXojflsZalyxSh31CIyHz2GZ-KuFpPsrTzBG0pe2YHnjyVzzNIy2XHQYwH-ddMDrQ-TKn4rydSm7PSLx9FwwCKaRV9GUfPszbPRRogdIJ8yuomUM7HRkkfddLZQOvw2QfKOAkznhAIc0QnS--uA", "icon_url_large": "IzMF03bi9WpSBq-S-ekoE33L-iLqGFHVaU25ZzQNQcXdB2ozio1RrlIWFK3UfvMYB8UsvjiMXojflsZalyxSh31CIyHz2GZ-KuFpPsrTzBG0pe2YHnjyVzzNIy3mEF96GuZAYT2I_TKn4OqQQ2rAQ-EoSwlRf6MN8TFBaMGLbBJo1tYI_DLoxRwuR1g4fMIAcwC3xWYeJLExwTEePJYDzy3ycsImSl5cmA", "icon_drag_url": "", "name": "Graffiti | Double (Violent Violet)", "market_hash_name": "Graffiti | Double (Violent Violet)", "market_name": "Graffiti | Double (Violent Violet)", "name_color": "D2D2D2", "background_color": "", "type": "Base Grade Graffiti", "tradable": 0, "marketable": 0, "commodity": 1, "market_tradable_restriction": "7", "descriptions": [{"type": "html", "value": "This graffiti can be applied to the in-game world. You can apply it until you run out of charges."}, {"type": "html", "value": " "}, {"type": "html", "value": "", "color": "00a000", "app_data": {"limited": 1}}, {"type": "html", "value": " "}, {"type": "html", "value": ""}], "actions": [{"name": "Inspect in Game...", "link": "steam://rungame/730/76561202255233023/+csgo_econ_action_preview%20S%owner_steamid%A%assetid%D11839025707683284751"}], "market_actions": [{"name": "Inspect in Game...", "link": "steam://rungame/730/76561202255233023/+csgo_econ_action_preview%20M%listingid%A%assetid%D11839025707683284751"}], "tags": [{"internal_name": "CSGO_Type_Spray", "name": "Graffiti", "category": "Type", "category_name": "Type"}, {"internal_name": "normal", "name": "Normal", "category": "Quality", "category_name": "Category"}, {"internal_name": "Rarity_Common", "name": "Base Grade", "category": "Rarity", "color": "b0c3d9", "category_name": "Quality"}, {"internal_name": "Tint14", "name": "Violent Violet", "category": "SprayColorCategory", "category_name": "Graffiti Color"}]}, "310776717_302028390": {"appid": "730", "classid": "310776717", "instanceid": "302028390", "icon_url": "-9a81dlWLwJ2UUGcVs_nsVtzdOEdtWwKGZZLQHTxDZ7I56KU0Zwwo4NUX4oFJZEHLbXH5ApeO4YmlhxYQknCRvCo04DEVlxkKgposem2LFZf2-r3cC9B-NW1q4OEmePmMqjFqWZU7Mxkh6fH8Imni1e3rhJpZWv0LNDHelI-NwuDrwPswO3s0JG4v5vJz3ZlvCkn-z-DyHWoV0Xo", "icon_url_large": "-9a81dlWLwJ2UUGcVs_nsVtzdOEdtWwKGZZLQHTxDZ7I56KU0Zwwo4NUX4oFJZEHLbXH5ApeO4YmlhxYQknCRvCo04DEVlxkKgposem2LFZf2-r3cC9B-NW1q4OEmePmMqjFqWZU7Mxkh9bN9J7yjRqyrhZuMDqgcdeQdAQ5aQ6C8gW-l7280MTuvZ7KnHVnuSYi43vbmRyyn1gSOQqCksKU", "icon_drag_url": "", "name": "G3SG1 | Polar Camo", "market_hash_name": "G3SG1 | Polar Camo (Field-Tested)", "market_name": "G3SG1 | Polar Camo (Field-Tested)", "name_color": "D2D2D2", "background_color": "", "type": "Consumer Grade Sniper Rifle", "tradable": 1, "marketable": 1, "commodity": 0, "market_tradable_restriction": "7", "descriptions": [{"type": "html", "value": "Exterior: Field-Tested"}, {"type": "html", "value": " "}, {"type": "html", "value": "The pricy G3SG1 lowers movement speed considerably but compensates with a higher rate of fire than other sniper rifles. It has been painted using an arctic camo hydrographic.\n\n<i>Snow is cold; death is colder</i>"}, {"type": "html", "value": " "}, {"type": "html", "value": "The Train Collection", "color": "9da1a9", "app_data": {"def_index": "65535", "is_itemset_name": 1}}, {"type": "html", "value": " "}], "actions": [{"name": "Inspect in Game...", "link": "steam://rungame/730/76561202255233023/+csgo_econ_action_preview%20S%owner_steamid%A%assetid%D3237540999667306581"}], "market_actions": [{"name": "Inspect in Game...", "link": "steam://rungame/730/76561202255233023/+csgo_econ_action_preview%20M%listingid%A%assetid%D3237540999667306581"}], "tags": [{"internal_name": "CSGO_Type_SniperRifle", "name": "Sniper Rifle", "category": "Type", "category_name": "Type"}, {"internal_name": "weapon_g3sg1", "name": "G3SG1", "category": "Weapon", "category_name": "Weapon"}, {"internal_name": "set_train", "name": "The Train Collection", "category": "ItemSet", "category_name": "Collection"}, {"internal_name": "normal", "name": "Normal", "category": "Quality", "category_name": "Category"}, {"internal_name": "Rarity_Common_Weapon", "name": "Consumer Grade", "category": "Rarity", "color": "b0c3d9", "category_name": "Quality"}, {"internal_name": "WearCategory2", "name": "Field-Tested", "category": "Exterior", "category_name": "Exterior"}]}}, "more": false, "more_start": false}